[{"PuzzleId":"26v8M","Fen":"r1b1k2r/ppp2pp1/3b1q2/5P2/4PN1p/4P3/PPP3Bn/R1BQK2R b KQkq - 1 13","Moves":"d6f4 e3f4 h4h3 h1h2 f6h4 e1e2","Rating":2062,"NbPlays":3020,"Popularity":93,"Themes":"advantage capturingDefender defensiveMove long master opening trappedPiece","OpeningFamily":"","Opening":"","OpeningVariation":"","ECO":"","OpeningTags":"Amar_Opening Amar_Opening_Paris_Gambit"},{"PuzzleId":"kmZtd","Fen":"rnbqk1nr/ppp2ppp/8/3p4/5b2/2N3P1/PPPPP2P/R1BQKB1R w KQkq - 0 6","Moves":"g3f4 d8h4","Rating":543,"NbPlays":687,"Popularity":98,"Themes":"mate mateIn1 oneMove opening","OpeningFamily":"","Opening":"","OpeningVariation":"","ECO":"","OpeningTags":"Amar_Opening Amar_Opening_Paris_Gambit"}]