[{"PuzzleId":"yS5JB","Fen":"2kr1b1r/pp4p1/4qn2/3pp1B1/8/5BN1/PPP3K1/RN1QR3 w - - 2 19","Moves":"g5f6 e6h3 g2f2 f8c5","Rating":1712,"NbPlays":82,"Popularity":79,"Themes":"advantage opening short","OpeningFamily":"","Opening":"","OpeningVariation":"","ECO":"","OpeningTags":"Caro-Kann_Defense Caro-Kann_Defense_Spike_Variation"},{"PuzzleId":"ip1bk","Fen":"r1b1r1k1/pp3ppp/8/q1b5/3Q2P1/2P2PB1/PP2N2P/R3KB1R w KQ - 1 16","Moves":"b2b4 c5d4 b4a5 d4c3 e1f2 c3a1","Rating":1408,"NbPlays":4491,"Popularity":93,"Themes":"advantage exposedKing long opening pin","OpeningFamily":"","Opening":"","OpeningVariation":"","ECO":"","OpeningTags":"Caro-Kann_Defense Caro-Kann_Defense_Spike_Variation"},{"PuzzleId":"VXQkz","Fen":"r1bqkbnr/pp1npppp/2p5/8/4N1P1/8/PPPPQP1P/R1B1KBNR b KQkq - 2 5","Moves":"g8f6 e4d6","Rating":1438,"NbPlays":1811,"Popularity":95,"Themes":"mate mateIn1 oneMove opening pin smotheredMate","OpeningFamily":"","Opening":"","OpeningVariation":"","ECO":"","OpeningTags":"Caro-Kann_Defense Caro-Kann_Defense_Spike_Variation"},{"PuzzleId":"JhxuH","Fen":"rn1qkb1r/pp2pp1p/2p3p1/3n2P1/2PPN3/8/PP2QP1P/R1B1K1NR b KQkq - 0 9","Moves":"d5c7 e4f6","Rating":983,"NbPlays":769,"Popularity":88,"Themes":"mate mateIn1 oneMove opening pin","OpeningFamily":"","Opening":"","OpeningVariation":"","ECO":"","OpeningTags":"Caro-Kann_Defense Caro-Kann_Defense_Spike_Variation"}]