[{"PuzzleId":"b7Vls","Fen":"r3kb1r/ppp2ppp/2np2n1/6P1/3pP2R/P4Nq1/1PPNK3/R1BQ1B2 w kq - 5 13","Moves":"h4h3 g6f4","Rating":1015,"NbPlays":62,"Popularity":100,"Themes":"mate mateIn1 oneMove opening","OpeningFamily":"","Opening":"","OpeningVariation":"","ECO":"","OpeningTags":"Center_Game Center_Game_Halasz-McDonnell_Gambit"},{"PuzzleId":"OoVGK","Fen":"r1b1kb1r/pp1pnBpp/1qn2p2/2p3N1/4PP2/2N5/PP4PP/R1BQK2R b KQkq - 1 9","Moves":"e8d8 g5e6","Rating":935,"NbPlays":72,"Popularity":67,"Themes":"mate mateIn1 oneMove opening pin","OpeningFamily":"","Opening":"","OpeningVariation":"","ECO":"","OpeningTags":"Center_Game Center_Game_Halasz-McDonnell_Gambit"},{"PuzzleId":"y6UZI","Fen":"r1bq1rk1/ppp1npp1/2np4/2b1P1NQ/3p1P2/8/PPP3PP/RNB2RK1 b - - 3 10","Moves":"e7g6 h5h7","Rating":831,"NbPlays":68,"Popularity":100,"Themes":"mate mateIn1 oneMove opening","OpeningFamily":"","Opening":"","OpeningVariation":"","ECO":"","OpeningTags":"Center_Game Center_Game_Halasz-McDonnell_Gambit"},{"PuzzleId":"4dIlK","Fen":"rn1q1rk1/ppp1bppp/1n6/4P3/3p2b1/3B1N2/PPPN2PP/R1B1QRK1 b - - 2 11","Moves":"b8c6 e1e4 f7f5 e5f6","Rating":1992,"NbPlays":530,"Popularity":97,"Themes":"advantage enPassant opening short","OpeningFamily":"","Opening":"","OpeningVariation":"","ECO":"","OpeningTags":"Center_Game Center_Game_Halasz-McDonnell_Gambit"},{"PuzzleId":"9V2ma","Fen":"r1bq1rk1/ppp2ppp/2n5/2bpP1N1/3pnP2/3B4/PPP1Q1PP/RNB2RK1 b - - 6 9","Moves":"h7h6 g5e4 d5e4 e2e4","Rating":1808,"NbPlays":86,"Popularity":84,"Themes":"advantage opening short","OpeningFamily":"","Opening":"","OpeningVariation":"","ECO":"","OpeningTags":"Center_Game Center_Game_Halasz-McDonnell_Gambit"},{"PuzzleId":"J6GNj","Fen":"rnbq1rk1/ppp1npp1/3p4/2b1P1NQ/3p1P2/8/PPP3PP/RNB1K2R b KQ - 3 9","Moves":"e7g6 h5h7","Rating":830,"NbPlays":57,"Popularity":100,"Themes":"mate mateIn1 oneMove opening","OpeningFamily":"","Opening":"","OpeningVariation":"","ECO":"","OpeningTags":"Center_Game Center_Game_Halasz-McDonnell_Gambit"},{"PuzzleId":"aukNP","Fen":"rnbq1rk1/ppp2ppp/5n2/2b1P3/3p4/3B1N2/PPP3PP/RNBQ1RK1 b - - 0 8","Moves":"f6d5 d3h7 g8h7 f3g5 h7g8 d1h5","Rating":1567,"NbPlays":1335,"Popularity":89,"Themes":"advantage attraction clearance kingsideAttack long opening sacrifice","OpeningFamily":"","Opening":"","OpeningVariation":"","ECO":"","OpeningTags":"Center_Game Center_Game_Halasz-McDonnell_Gambit"},{"PuzzleId":"5xYpG","Fen":"rnbq1rk1/ppppbppp/n7/4P3/2BQ1P2/5N2/PPP3PP/RNB2RK1 w - - 5 9","Moves":"f4f5 e7c5 d4c5 a6c5","Rating":945,"NbPlays":102,"Popularity":74,"Themes":"advantage opening pin short","OpeningFamily":"","Opening":"","OpeningVariation":"","ECO":"","OpeningTags":"Center_Game Center_Game_Halasz-McDonnell_Gambit"},{"PuzzleId":"QrFhb","Fen":"r1bqk2r/ppp2p1p/5bp1/4Pn2/2B5/1Q6/PPP3PP/RNB2RK1 b kq - 2 12","Moves":"f6e5 b3b5 e8f8 b5e5 d8d4 e5d4","Rating":2458,"NbPlays":94,"Popularity":86,"Themes":"crushing fork long opening","OpeningFamily":"","Opening":"","OpeningVariation":"","ECO":"","OpeningTags":"Center_Game Center_Game_Halasz-McDonnell_Gambit"},{"PuzzleId":"M0zin","Fen":"r2qkbnr/ppp3pp/8/3pn3/3p2b1/P2B1N2/1PP1Q1PP/RNB1K2R b KQkq - 1 9","Moves":"d8e7 e2e5 g4f3 e5e7 g8e7 g2f3","Rating":1620,"NbPlays":6196,"Popularity":94,"Themes":"advantage exposedKing long opening","OpeningFamily":"","Opening":"","OpeningVariation":"","ECO":"","OpeningTags":"Center_Game Center_Game_Halasz-McDonnell_Gambit"},{"PuzzleId":"j1hyx","Fen":"rnbqkb1r/pppp1ppp/8/3nP3/2Pp1P2/8/PP4PP/RNBQKBNR b KQkq c3 0 5","Moves":"d4c3 d1d5 c3b2 c1b2","Rating":1181,"NbPlays":14,"Popularity":0,"Themes":"advantage hangingPiece opening short","OpeningFamily":"","Opening":"","OpeningVariation":"","ECO":"","OpeningTags":"Center_Game Center_Game_Halasz-McDonnell_Gambit"},{"PuzzleId":"apEpy","Fen":"r3k1nr/1pp2pQp/p7/4P3/5P2/3nq3/PP2B1PP/RN2K1NR w kq - 7 16","Moves":"e1d1 e3c1","Rating":1027,"NbPlays":1331,"Popularity":99,"Themes":"opening","OpeningFamily":"","Opening":"","OpeningVariation":"","ECO":"","OpeningTags":"Center_Game Center_Game_Halasz-McDonnell_Gambit"},{"PuzzleId":"DhlQe","Fen":"r1bq1rk1/ppp1n1p1/1bn4p/3p2NQ/3p1P2/P2B2NP/1PP3P1/R1B2RK1 b - - 1 13","Moves":"e7f5 h5g6 h6g5 g3f5 c8f5 d3f5 f8f5 g6f5","Rating":2343,"NbPlays":1504,"Popularity":90,"Themes":"advantage opening veryLong","OpeningFamily":"","Opening":"","OpeningVariation":"","ECO":"","OpeningTags":"Center_Game Center_Game_Halasz-McDonnell_Gambit"},{"PuzzleId":"adK6O","Fen":"r2q1rk1/pppbbppp/2n5/3nP3/3pQ3/3B1N1P/PPPN2P1/R1B2RK1 b - - 2 12","Moves":"d7e6 e4h7","Rating":601,"NbPlays":149,"Popularity":59,"Themes":"kingsideAttack mate mateIn1 oneMove opening","OpeningFamily":"","Opening":"","OpeningVariation":"","ECO":"","OpeningTags":"Center_Game Center_Game_Halasz-McDonnell_Gambit"},{"PuzzleId":"LyCJZ","Fen":"rn3rk1/ppq2ppp/8/2p2b1Q/3pNb2/7P/PPPN2P1/R1B2RK1 b - - 4 14","Moves":"g7g6 e4f6 g8g7 h5h7 g7f6 d2e4","Rating":1982,"NbPlays":180,"Popularity":99,"Themes":"advantage kingsideAttack long opening sacrifice","OpeningFamily":"","Opening":"","OpeningVariation":"","ECO":"","OpeningTags":"Center_Game Center_Game_Halasz-McDonnell_Gambit"},{"PuzzleId":"xmx20","Fen":"r2qk1nr/ppp2ppp/2n5/2bpP3/3p1P2/3Q1N2/PPP3PP/RNB2RK1 b kq - 2 8","Moves":"c6b4 d3b5 c7c6 b5c5","Rating":1093,"NbPlays":126,"Popularity":66,"Themes":"advantage fork opening short","OpeningFamily":"","Opening":"","OpeningVariation":"","ECO":"","OpeningTags":"Center_Game Center_Game_Halasz-McDonnell_Gambit"},{"PuzzleId":"3r9u7","Fen":"r2q1rk1/1pp2pp1/p1np3p/2bnP3/3pQPb1/P2B1N2/1PPN2PP/R1B2R1K b - - 2 12","Moves":"d6e5 e4h7","Rating":1624,"NbPlays":50,"Popularity":16,"Themes":"mate mateIn1 oneMove opening","OpeningFamily":"","Opening":"","OpeningVariation":"","ECO":"","OpeningTags":"Center_Game Center_Game_Halasz-McDonnell_Gambit"},{"PuzzleId":"VpC0z","Fen":"r1bq2r1/ppp1b1pk/5n1p/4pP2/3p4/6QN/PPP3PP/R1B2RK1 b - - 3 17","Moves":"e7d6 h3g5 h6g5 g3h3 f6h5 h3h5","Rating":1965,"NbPlays":45,"Popularity":100,"Themes":"clearance long mate mateIn3 opening sacrifice","OpeningFamily":"","Opening":"","OpeningVariation":"","ECO":"","OpeningTags":"Center_Game Center_Game_Halasz-McDonnell_Gambit"},{"PuzzleId":"3X7Wq","Fen":"r1bq1rk1/pppn1pp1/2n5/2b1P1NQ/3p1B2/8/PPP3PP/RN3RK1 b - - 3 12","Moves":"f7f6 h5h7","Rating":929,"NbPlays":43,"Popularity":100,"Themes":"mate mateIn1 oneMove opening","OpeningFamily":"","Opening":"","OpeningVariation":"","ECO":"","OpeningTags":"Center_Game Center_Game_Halasz-McDonnell_Gambit"},{"PuzzleId":"bmdWd","Fen":"r1bq1rk1/1ppn1pp1/p1n5/2b1P1NQ/3p4/P6P/1PP3P1/RNB2RK1 b - - 3 13","Moves":"d7e5 h5h7","Rating":854,"NbPlays":286,"Popularity":100,"Themes":"mate mateIn1 oneMove opening","OpeningFamily":"","Opening":"","OpeningVariation":"","ECO":"","OpeningTags":"Center_Game Center_Game_Halasz-McDonnell_Gambit"},{"PuzzleId":"jvvLM","Fen":"r1b1k1nr/pppp1Bpp/2n5/2b5/3pqP2/5N2/PPP2KPP/RNBQ3R b kq - 0 7","Moves":"e8f7 f3g5 f7f8 g5e4","Rating":1020,"NbPlays":352,"Popularity":94,"Themes":"crushing fork opening short","OpeningFamily":"","Opening":"","OpeningVariation":"","ECO":"","OpeningTags":"Center_Game Center_Game_Halasz-McDonnell_Gambit"},{"PuzzleId":"7V4vS","Fen":"r2q1rk1/bpp2pp1/p1n5/4n1N1/3p3Q/7P/PPP3P1/R1B2R1K b - - 3 17","Moves":"d4d3 h4h7","Rating":905,"NbPlays":182,"Popularity":100,"Themes":"mate mateIn1 oneMove opening","OpeningFamily":"","Opening":"","OpeningVariation":"","ECO":"","OpeningTags":"Center_Game Center_Game_Halasz-McDonnell_Gambit"},{"PuzzleId":"YHIzb","Fen":"r2qkbnr/3b1Npp/p1np4/1ppN1P2/2B1P3/8/PP4PP/R1BQK2R b KQkq - 0 11","Moves":"e8f7 d1h5 g7g6 f5g6 f7g7 e1g1","Rating":2496,"NbPlays":429,"Popularity":90,"Themes":"castling crushing defensiveMove long opening","OpeningFamily":"","Opening":"","OpeningVariation":"","ECO":"","OpeningTags":"Center_Game Center_Game_Halasz-McDonnell_Gambit"},{"PuzzleId":"a9ZmG","Fen":"r3kbnr/ppp3pp/2n5/3pP3/3p3q/3B1QPP/PPP5/RNB1K2R b KQkq - 0 10","Moves":"c6e5 f3f8 e8f8 g3h4 e5d3 c2d3","Rating":1884,"NbPlays":336,"Popularity":69,"Themes":"advantage long opening","OpeningFamily":"","Opening":"","OpeningVariation":"","ECO":"","OpeningTags":"Center_Game Center_Game_Halasz-McDonnell_Gambit"},{"PuzzleId":"o9wRB","Fen":"r1b2rk1/ppp1qpp1/2n2n2/4P1NQ/1b6/2N5/PP4PP/R1B1R1K1 w - - 4 15","Moves":"e5f6 e7e1","Rating":1585,"NbPlays":25,"Popularity":69,"Themes":"hangingPiece kingsideAttack mate mateIn1 oneMove opening","OpeningFamily":"","Opening":"","OpeningVariation":"","ECO":"","OpeningTags":"Center_Game Center_Game_Halasz-McDonnell_Gambit"},{"PuzzleId":"xKRUD","Fen":"r2qkbnr/pp1n2pp/3pb3/2p2pN1/3p1P2/3B4/PPP3PP/RNBQK2R b KQkq - 1 9","Moves":"d8f6 d1e2 e8c8 e2e6 h7h6 e6f6","Rating":2204,"NbPlays":197,"Popularity":86,"Themes":"advantage long opening","OpeningFamily":"","Opening":"","OpeningVariation":"","ECO":"","OpeningTags":"Center_Game Center_Game_Halasz-McDonnell_Gambit"},{"PuzzleId":"S10ic","Fen":"r1bq1rk1/ppp1bppp/5n2/6N1/3p4/3Q4/PPP3PP/RNB2RK1 b - - 0 11","Moves":"f6g4 d3h7","Rating":542,"NbPlays":149,"Popularity":100,"Themes":"kingsideAttack mate mateIn1 oneMove opening","OpeningFamily":"","Opening":"","OpeningVariation":"","ECO":"","OpeningTags":"Center_Game Center_Game_Halasz-McDonnell_Gambit"},{"PuzzleId":"Y30ZB","Fen":"rn1q1bnr/pp3k1p/6p1/2p2P2/3pp3/8/PPP3PP/RNBQ1RK1 b - - 0 10","Moves":"g6f5 d1h5 f7g7 f1f5","Rating":2001,"NbPlays":154,"Popularity":83,"Themes":"advantage intermezzo opening short","OpeningFamily":"","Opening":"","OpeningVariation":"","ECO":"","OpeningTags":"Center_Game Center_Game_Halasz-McDonnell_Gambit"},{"PuzzleId":"s7JC5","Fen":"r2q1rk1/ppp1n1p1/2n2pP1/2b1p1N1/3p2PQ/8/PPP4P/RNB2RK1 b - - 0 14","Moves":"f6g5 h4h7","Rating":1194,"NbPlays":54,"Popularity":86,"Themes":"mate mateIn1 oneMove opening","OpeningFamily":"","Opening":"","OpeningVariation":"","ECO":"","OpeningTags":"Center_Game Center_Game_Halasz-McDonnell_Gambit"},{"PuzzleId":"WvTaf","Fen":"rnbq1rk1/ppp2ppp/1n1p4/4P3/4QP2/3B1N2/PPP3PP/RN2K2R b KQ - 1 10","Moves":"d6d5 e4h7","Rating":534,"NbPlays":160,"Popularity":100,"Themes":"kingsideAttack mate mateIn1 oneMove opening","OpeningFamily":"","Opening":"","OpeningVariation":"","ECO":"","OpeningTags":"Center_Game Center_Game_Halasz-McDonnell_Gambit"},{"PuzzleId":"Bfsqp","Fen":"r2qkb1r/ppp2ppp/2n2n2/4P3/3p2b1/3B1N2/PPP3PP/RNBQ1RK1 b kq - 0 8","Moves":"c6e5 d1e1 g4f3 e1e5 d8e7 e5e7","Rating":2171,"NbPlays":460,"Popularity":85,"Themes":"advantage long opening pin","OpeningFamily":"","Opening":"","OpeningVariation":"","ECO":"","OpeningTags":"Center_Game Center_Game_Halasz-McDonnell_Gambit"},{"PuzzleId":"nBJ72","Fen":"rnbq1rk1/ppp1npp1/8/2bpP1NQ/3p1P2/6P1/PPP4P/RNB2RK1 b - - 3 11","Moves":"e7f5 h5h7","Rating":870,"NbPlays":130,"Popularity":86,"Themes":"mate mateIn1 oneMove opening","OpeningFamily":"","Opening":"","OpeningVariation":"","ECO":"","OpeningTags":"Center_Game Center_Game_Halasz-McDonnell_Gambit"},{"PuzzleId":"NAp4T","Fen":"r1bq2k1/ppp4p/2n1rnNQ/6B1/8/3p4/PPP3PP/RN3RK1 b - - 0 17","Moves":"f6g4 f1f8 d8f8 h6f8","Rating":1459,"NbPlays":1937,"Popularity":97,"Themes":"fork mate mateIn2 opening short","OpeningFamily":"","Opening":"","OpeningVariation":"","ECO":"","OpeningTags":"Center_Game Center_Game_Halasz-McDonnell_Gambit"},{"PuzzleId":"GUul6","Fen":"r1bq1r2/pppp1p2/2n3pk/2bnP1N1/5P1Q/3p4/PPP3PP/RNB2R1K b - - 1 12","Moves":"h6g7 h4h7","Rating":775,"NbPlays":337,"Popularity":100,"Themes":"mate mateIn1 oneMove opening","OpeningFamily":"","Opening":"","OpeningVariation":"","ECO":"","OpeningTags":"Center_Game Center_Game_Halasz-McDonnell_Gambit"},{"PuzzleId":"euCKr","Fen":"r1bqk2r/ppppbppp/2n5/4P3/4nP2/2PB1N2/P5PP/RNBQK2R b KQkq - 2 8","Moves":"e7h4 g2g3 h4g3 h2g3","Rating":1299,"NbPlays":2035,"Popularity":100,"Themes":"advantage defensiveMove opening short","OpeningFamily":"","Opening":"","OpeningVariation":"","ECO":"","OpeningTags":"Center_Game Center_Game_Halasz-McDonnell_Gambit"},{"PuzzleId":"nTmjF","Fen":"r1bqrbk1/ppp2ppp/2np4/6N1/4nP2/P1NQ4/1PP1B1PP/R1B2RK1 b - - 1 11","Moves":"e4c3 d3h7","Rating":1047,"NbPlays":49,"Popularity":69,"Themes":"kingsideAttack mate mateIn1 oneMove opening","OpeningFamily":"","Opening":"","OpeningVariation":"","ECO":"","OpeningTags":"Center_Game Center_Game_Halasz-McDonnell_Gambit"},{"PuzzleId":"NPley","Fen":"r1bqk1nr/ppp2ppp/2n5/b3P3/1P1p1P2/P1N2N2/6PP/R1BQKB1R b KQkq - 0 9","Moves":"c6b4 a3b4 a5b4 d1a4 c8d7 a4b4","Rating":1870,"NbPlays":36,"Popularity":63,"Themes":"advantage fork long opening","OpeningFamily":"","Opening":"","OpeningVariation":"","ECO":"","OpeningTags":"Center_Game Center_Game_Halasz-McDonnell_Gambit"},{"PuzzleId":"PVLMv","Fen":"r1b2rk1/ppp2ppp/2n2n2/3q4/5P2/4QN2/PPP3PP/RN2R2K b - - 0 12","Moves":"f8e8 e3e8 f6e8 e1e8","Rating":418,"NbPlays":239,"Popularity":89,"Themes":"backRankMate master mate mateIn2 opening short","OpeningFamily":"","Opening":"","OpeningVariation":"","ECO":"","OpeningTags":"Center_Game Center_Game_Halasz-McDonnell_Gambit"},{"PuzzleId":"CKmE2","Fen":"r2qk2r/pppbbppp/8/3pnPNQ/1n1p1B2/3B3P/PPP3P1/RN3RK1 b kq - 1 12","Moves":"e5d3 h5f7","Rating":1439,"NbPlays":45,"Popularity":87,"Themes":"attackingF2F7 mate mateIn1 oneMove opening","OpeningFamily":"","Opening":"","OpeningVariation":"","ECO":"","OpeningTags":"Center_Game Center_Game_Halasz-McDonnell_Gambit"},{"PuzzleId":"HDfWU","Fen":"rnbqk2r/ppppbppp/8/8/3QPPn1/5N2/PPP1B1PP/RNB1K2R b KQkq - 0 6","Moves":"b8c6 d4g7 e7f6 g7g4","Rating":1154,"NbPlays":851,"Popularity":88,"Themes":"crushing fork opening short","OpeningFamily":"","Opening":"","OpeningVariation":"","ECO":"","OpeningTags":"Center_Game Center_Game_Halasz-McDonnell_Gambit"},{"PuzzleId":"uifZD","Fen":"r2q1rk1/1pp1npp1/1bn5/p4BNQ/5P2/P2p4/1PP3PP/R1B2R1K b - - 1 15","Moves":"e7f5 h5h7","Rating":888,"NbPlays":244,"Popularity":91,"Themes":"mate mateIn1 oneMove opening","OpeningFamily":"","Opening":"","OpeningVariation":"","ECO":"","OpeningTags":"Center_Game Center_Game_Halasz-McDonnell_Gambit"},{"PuzzleId":"c42XD","Fen":"r1b1k1nr/pp1pqp1p/2nb2p1/2pQP3/2Bp1P2/8/PPPB2PP/RN2K1NR b KQkq - 0 8","Moves":"g8f6 d5d6 e7d6 e5d6","Rating":1724,"NbPlays":144,"Popularity":67,"Themes":"advantage opening short","OpeningFamily":"","Opening":"","OpeningVariation":"","ECO":"","OpeningTags":"Center_Game Center_Game_Halasz-McDonnell_Gambit"},{"PuzzleId":"52On1","Fen":"rnb4k/ppp1qBpp/3b4/4r3/2Q2B2/2P5/PP4PP/RN3RK1 b - - 4 16","Moves":"e5e4 f4d6 e4c4 d6e7","Rating":1226,"NbPlays":168,"Popularity":80,"Themes":"crushing opening short","OpeningFamily":"","Opening":"","OpeningVariation":"","ECO":"","OpeningTags":"Center_Game Center_Game_Halasz-McDonnell_Gambit"},{"PuzzleId":"wqIMQ","Fen":"r2qkb1r/ppp2ppp/2n2n2/4P3/2Bp2b1/5N2/PPP3PP/RNBQ1RK1 b kq - 0 8","Moves":"c6e5 d1e1 g4f3 e1e5 d8e7 e5e7","Rating":2312,"NbPlays":155,"Popularity":78,"Themes":"advantage long opening pin","OpeningFamily":"","Opening":"","OpeningVariation":"","ECO":"","OpeningTags":"Center_Game Center_Game_Halasz-McDonnell_Gambit"},{"PuzzleId":"t4UXh","Fen":"r1bq2kr/pp1pb1pp/2n5/2p1P1P1/3p4/5Q2/PPP3PP/RNB2RK1 b - - 2 11","Moves":"d7d5 f3f7","Rating":958,"NbPlays":95,"Popularity":100,"Themes":"mate mateIn1 oneMove opening","OpeningFamily":"","Opening":"","OpeningVariation":"","ECO":"","OpeningTags":"Center_Game Center_Game_Halasz-McDonnell_Gambit"},{"PuzzleId":"Hekv7","Fen":"r1bq1r2/ppp2ppk/2n5/2bnP3/3pN3/5N2/PPP3PP/R1BQ1RK1 b - - 1 11","Moves":"c5e7 f3g5 e7g5 e4g5 h7g8 d1h5","Rating":2199,"NbPlays":258,"Popularity":96,"Themes":"advantage long opening","OpeningFamily":"","Opening":"","OpeningVariation":"","ECO":"","OpeningTags":"Center_Game Center_Game_Halasz-McDonnell_Gambit"},{"PuzzleId":"A6Atm","Fen":"rnb1kbnr/pppp1ppp/8/8/2BQ1P2/8/PPP1N2q/RNB1K1R1 b Qkq - 0 7","Moves":"b8c6 d4e4 f8e7 g1h1","Rating":2332,"NbPlays":2216,"Popularity":94,"Themes":"advantage opening short","OpeningFamily":"","Opening":"","OpeningVariation":"","ECO":"","OpeningTags":"Center_Game Center_Game_Halasz-McDonnell_Gambit"},{"PuzzleId":"npZSH","Fen":"r2q1rk1/ppp1npp1/2n3b1/2bpP1N1/5PPQ/3p4/PPP4P/RNB2R1K b - - 1 13","Moves":"d3c2 f4f5 c2b1b a1b1","Rating":1948,"NbPlays":193,"Popularity":99,"Themes":"advantage opening short","OpeningFamily":"","Opening":"","OpeningVariation":"","ECO":"","OpeningTags":"Center_Game Center_Game_Halasz-McDonnell_Gambit"},{"PuzzleId":"Uw9ob","Fen":"r2qkb1r/1b1pn2p/p4p2/2p5/2p2P1Q/2N5/PPP3PP/R1B1R1K1 b kq - 1 14","Moves":"h8g8 h4h5 g8g6 f4f5 e8f7 f5g6","Rating":1938,"NbPlays":274,"Popularity":92,"Themes":"advantage long opening","OpeningFamily":"","Opening":"","OpeningVariation":"","ECO":"","OpeningTags":"Center_Game Center_Game_Halasz-McDonnell_Gambit"},{"PuzzleId":"iwBC0","Fen":"rnbqk2r/ppp1npbp/3p2p1/6N1/2BpPP2/8/PPP3PP/RNBQ1RK1 b kq - 3 7","Moves":"e8g8 f4f5 d6d5 f5g6","Rating":2216,"NbPlays":190,"Popularity":87,"Themes":"advantage opening short","OpeningFamily":"","Opening":"","OpeningVariation":"","ECO":"","OpeningTags":"Center_Game Center_Game_Halasz-McDonnell_Gambit"},{"PuzzleId":"WDB3e","Fen":"rnbqkbnr/p2p1ppp/8/1pp5/2BpPP2/8/PPP3PP/RNBQK1NR w KQkq - 0 5","Moves":"c4b5 d8a5 c2c3 a5b5","Rating":1186,"NbPlays":144,"Popularity":87,"Themes":"advantage fork opening short","OpeningFamily":"","Opening":"","OpeningVariation":"","ECO":"","OpeningTags":"Center_Game Center_Game_Halasz-McDonnell_Gambit"},{"PuzzleId":"C2wPH","Fen":"r1bqrk1Q/pppp2p1/2n5/2b1P1N1/3p1P2/8/PPP3PP/RNB2K2 b - - 6 16","Moves":"f8e7 h8g7","Rating":788,"NbPlays":185,"Popularity":100,"Themes":"mate mateIn1 oneMove opening","OpeningFamily":"","Opening":"","OpeningVariation":"","ECO":"","OpeningTags":"Center_Game Center_Game_Halasz-McDonnell_Gambit"},{"PuzzleId":"yoFcq","Fen":"r2q1rk1/pppnbppp/2n5/4P3/3pQ3/P2B3P/1PP3P1/RNB2RK1 b - - 2 12","Moves":"c6e5 e4h7","Rating":611,"NbPlays":97,"Popularity":64,"Themes":"kingsideAttack mate mateIn1 oneMove opening","OpeningFamily":"","Opening":"","OpeningVariation":"","ECO":"","OpeningTags":"Center_Game Center_Game_Halasz-McDonnell_Gambit"},{"PuzzleId":"SMdJ3","Fen":"r1bq1r2/pppp2p1/2n4k/2bnPpN1/3p1P1Q/8/PPP3PP/RNB2RK1 b - - 1 11","Moves":"h6g6 h4h7","Rating":836,"NbPlays":165,"Popularity":100,"Themes":"mate mateIn1 oneMove opening","OpeningFamily":"","Opening":"","OpeningVariation":"","ECO":"","OpeningTags":"Center_Game Center_Game_Halasz-McDonnell_Gambit"},{"PuzzleId":"ABGom","Fen":"r2q1r1k/ppp1n1pp/2np1p2/2b2P1Q/2BpPR2/7P/PPP3P1/RNB3K1 b - - 5 12","Moves":"d8e8 h5h7 h8h7 f4h4 e8h5 h4h5","Rating":1346,"NbPlays":90,"Popularity":64,"Themes":"attraction kingsideAttack long mate mateIn3 opening sacrifice","OpeningFamily":"","Opening":"","OpeningVariation":"","ECO":"","OpeningTags":"Center_Game Center_Game_Halasz-McDonnell_Gambit"},{"PuzzleId":"u2WVM","Fen":"r1bqk1nr/ppp2ppp/8/2bpP3/3p1P2/3Q1N2/PPP3PP/RNB2RK1 b kq - 0 8","Moves":"g8e7 d3b5 d8d7 b5c5","Rating":1264,"NbPlays":470,"Popularity":88,"Themes":"advantage fork opening short","OpeningFamily":"","Opening":"","OpeningVariation":"","ECO":"","OpeningTags":"Center_Game Center_Game_Halasz-McDonnell_Gambit"},{"PuzzleId":"oAV9L","Fen":"r1bq1rk1/pppp1ppp/2n5/2b1P1N1/3p1P2/3Q4/PPP3PP/RNB2R1K b - - 4 10","Moves":"h7h6 d3h7","Rating":583,"NbPlays":75,"Popularity":100,"Themes":"mate mateIn1 oneMove opening","OpeningFamily":"","Opening":"","OpeningVariation":"","ECO":"","OpeningTags":"Center_Game Center_Game_Halasz-McDonnell_Gambit"},{"PuzzleId":"wwdHh","Fen":"r1bq1rk1/pppn1pp1/2n5/2b1P1NQ/3p4/7P/PPP3P1/RNB2RK1 b - - 3 12","Moves":"f7f6 h5h7","Rating":841,"NbPlays":245,"Popularity":96,"Themes":"mate mateIn1 oneMove opening","OpeningFamily":"","Opening":"","OpeningVariation":"","ECO":"","OpeningTags":"Center_Game Center_Game_Halasz-McDonnell_Gambit"},{"PuzzleId":"kwDcT","Fen":"r1bq1r2/ppp2pp1/2npN1k1/2bnP3/3p1PQ1/8/PPP3PP/RNB2RK1 b - - 1 11","Moves":"g6h7 g4g7","Rating":1520,"NbPlays":1149,"Popularity":85,"Themes":"mate mateIn1 oneMove opening","OpeningFamily":"","Opening":"","OpeningVariation":"","ECO":"","OpeningTags":"Center_Game Center_Game_Halasz-McDonnell_Gambit"},{"PuzzleId":"pxvxF","Fen":"r1bqkbnr/pp1p1ppp/2n5/2p4Q/2BpPP2/8/PPP3PP/RNB1K1NR b KQkq - 3 5","Moves":"g8f6 h5f7","Rating":647,"NbPlays":479,"Popularity":95,"Themes":"attackingF2F7 mate mateIn1 oneMove opening","OpeningFamily":"","Opening":"","OpeningVariation":"","ECO":"","OpeningTags":"Center_Game Center_Game_Halasz-McDonnell_Gambit"},{"PuzzleId":"GgECD","Fen":"r1bq1rk1/ppp1npp1/2n5/2b1p1N1/5P1Q/3p4/PPP3PP/RNB2R1K b - - 1 12","Moves":"e7g6 h4h7","Rating":876,"NbPlays":109,"Popularity":92,"Themes":"mate mateIn1 oneMove opening","OpeningFamily":"","Opening":"","OpeningVariation":"","ECO":"","OpeningTags":"Center_Game Center_Game_Halasz-McDonnell_Gambit"},{"PuzzleId":"Lw9FB","Fen":"r2qk1nr/ppp2ppp/2n5/4P3/1bBp2b1/5N2/PPPB2PP/RN1QK2R b KQkq - 4 8","Moves":"c6e5 f3e5 b4d2 d1d2","Rating":1877,"NbPlays":29,"Popularity":37,"Themes":"advantage hangingPiece opening short","OpeningFamily":"","Opening":"","OpeningVariation":"","ECO":"","OpeningTags":"Center_Game Center_Game_Halasz-McDonnell_Gambit"},{"PuzzleId":"v7OeO","Fen":"r1b2rk1/ppp1qpp1/8/4n1N1/1bNp2nQ/8/PPP3PP/R1B2RK1 b - - 1 15","Moves":"e5g6 h4h7","Rating":1126,"NbPlays":27,"Popularity":74,"Themes":"mate mateIn1 oneMove opening","OpeningFamily":"","Opening":"","OpeningVariation":"","ECO":"","OpeningTags":"Center_Game Center_Game_Halasz-McDonnell_Gambit"},{"PuzzleId":"9dUUP","Fen":"r2qk1nr/ppp2ppp/2np4/2b1P3/2Bp1P2/1Q6/PPP3PP/RNB1K2R b KQkq - 2 8","Moves":"d8e7 b3b7 a8b8 b7c6","Rating":1752,"NbPlays":2773,"Popularity":92,"Themes":"crushing fork opening short","OpeningFamily":"","Opening":"","OpeningVariation":"","ECO":"","OpeningTags":"Center_Game Center_Game_Halasz-McDonnell_Gambit"},{"PuzzleId":"nv0Ee","Fen":"r1b2rk1/ppp3p1/2npp1P1/2bn3Q/8/3p4/PPP3PP/RNB2RK1 w - - 0 14","Moves":"g1h1 f8f1","Rating":618,"NbPlays":244,"Popularity":86,"Themes":"backRankMate hangingPiece mate mateIn1 oneMove opening","OpeningFamily":"","Opening":"","OpeningVariation":"","ECO":"","OpeningTags":"Center_Game Center_Game_Halasz-McDonnell_Gambit"},{"PuzzleId":"6zMbH","Fen":"r2q1rk1/ppp2pbp/2np1np1/4P3/3p1Pb1/P2B1N2/1PPN2PP/R1B1QRK1 b - - 0 10","Moves":"f8e8 e1g3 d6e5 f4e5 f6d5 g3g4","Rating":2382,"NbPlays":260,"Popularity":75,"Themes":"advantage long opening","OpeningFamily":"","Opening":"","OpeningVariation":"","ECO":"","OpeningTags":"Center_Game Center_Game_Halasz-McDonnell_Gambit"},{"PuzzleId":"ZEbJy","Fen":"r1bq1rk1/ppp2ppp/2np1b2/8/4PP2/3BQ3/PPP3PP/RN2NRK1 w - - 1 13","Moves":"b1c3 f6d4 e3d4 c6d4","Rating":1164,"NbPlays":170,"Popularity":100,"Themes":"advantage opening pin short","OpeningFamily":"","Opening":"","OpeningVariation":"","ECO":"","OpeningTags":"Center_Game Center_Game_Halasz-McDonnell_Gambit"},{"PuzzleId":"X1fNa","Fen":"rnb2r2/ppp1qpkB/3b2p1/6N1/5P1Q/4p2P/PPP3P1/RN3RK1 w - - 4 15","Moves":"h7g8 f8g8 h4h7 g7f8 h7h6 f8e8","Rating":1820,"NbPlays":473,"Popularity":93,"Themes":"advantage hangingPiece long opening","OpeningFamily":"","Opening":"","OpeningVariation":"","ECO":"","OpeningTags":"Center_Game Center_Game_Halasz-McDonnell_Gambit"},{"PuzzleId":"DvBKq","Fen":"r1bqk2r/ppp1nppp/2n5/1Bb5/3NpP2/2P1B3/PP4PP/RN1QK2R b KQkq - 2 8","Moves":"e8g8 d4c6 d8d1 e1d1 b7c6 e3c5","Rating":1825,"NbPlays":142,"Popularity":86,"Themes":"advantage long opening","OpeningFamily":"","Opening":"","OpeningVariation":"","ECO":"","OpeningTags":"Center_Game Center_Game_Halasz-McDonnell_Gambit"},{"PuzzleId":"wH9di","Fen":"r1bq1rk1/1pp2ppp/1bn5/p4n2/3pNP2/P2B1N1Q/1PP3PP/R1B2RK1 b - - 6 12","Moves":"f5e3 e4f6 g7f6 h3h7","Rating":1578,"NbPlays":1629,"Popularity":94,"Themes":"kingsideAttack mate mateIn2 opening sacrifice short","OpeningFamily":"","Opening":"","OpeningVariation":"","ECO":"","OpeningTags":"Center_Game Center_Game_Halasz-McDonnell_Gambit"},{"PuzzleId":"9eN4Q","Fen":"rnbqk2r/pppp1ppp/8/2b1P3/5P2/2NBpN2/PPP3PP/R2QK2R b KQkq - 3 8","Moves":"e8g8 d3h7 g8h7 f3g5 d8g5 f4g5","Rating":1757,"NbPlays":150,"Popularity":27,"Themes":"attraction crushing kingsideAttack long opening sacrifice","OpeningFamily":"","Opening":"","OpeningVariation":"","ECO":"","OpeningTags":"Center_Game Center_Game_Halasz-McDonnell_Gambit"},{"PuzzleId":"jxLxF","Fen":"r2qkbnr/pp4pp/8/2ppn3/3p2b1/PP1B1N2/2P3PP/RNBQ1RK1 b kq - 1 10","Moves":"g8f6 d1e1 g4f3 e1e5","Rating":2298,"NbPlays":208,"Popularity":90,"Themes":"advantage opening pin short","OpeningFamily":"","Opening":"","OpeningVariation":"","ECO":"","OpeningTags":"Center_Game Center_Game_Halasz-McDonnell_Gambit"},{"PuzzleId":"C5f90","Fen":"r1bq1rk1/ppp1bppp/2n5/7Q/3p4/3B3P/PPP3P1/RNB1R1K1 b - - 2 12","Moves":"h7h6 c1h6 g7g6 d3g6","Rating":1257,"NbPlays":846,"Popularity":83,"Themes":"advantage opening short","OpeningFamily":"","Opening":"","OpeningVariation":"","ECO":"","OpeningTags":"Center_Game Center_Game_Halasz-McDonnell_Gambit"},{"PuzzleId":"Z5cQS","Fen":"r1bq1rk1/ppp1npp1/2np4/2b1P1NQ/3p1P2/P7/1PP3PP/RNB1K2R b KQ - 3 10","Moves":"f7f6 h5h7","Rating":1306,"NbPlays":8,"Popularity":47,"Themes":"mate mateIn1 oneMove opening","OpeningFamily":"","Opening":"","OpeningVariation":"","ECO":"","OpeningTags":"Center_Game Center_Game_Halasz-McDonnell_Gambit"},{"PuzzleId":"tDGM3","Fen":"r2qk2r/ppp2ppp/2n5/2bpPn2/1P1p1Pb1/P2B1N2/2P3PP/RNBQ1RK1 b kq - 0 9","Moves":"f5e3 c1e3 d4e3 b4c5","Rating":1476,"NbPlays":145,"Popularity":84,"Themes":"advantage opening short","OpeningFamily":"","Opening":"","OpeningVariation":"","ECO":"","OpeningTags":"Center_Game Center_Game_Halasz-McDonnell_Gambit"},{"PuzzleId":"BC5oE","Fen":"r1bqk2r/1p1p1pbp/p1n2Pp1/2p5/3pP2N/8/PPP3PP/RNBQ1RK1 b kq - 0 10","Moves":"g7f6 d1f3 e8g8 f3f6 d8f6 f1f6","Rating":1861,"NbPlays":2506,"Popularity":93,"Themes":"advantage long opening","OpeningFamily":"","Opening":"","OpeningVariation":"","ECO":"","OpeningTags":"Center_Game Center_Game_Halasz-McDonnell_Gambit"},{"PuzzleId":"wDfex","Fen":"rn3rk1/ppp2pp1/3n1q2/2b2bNQ/3p1P2/7R/PPP3PP/RNB3K1 b - - 7 13","Moves":"f6g6 h5h8","Rating":1166,"NbPlays":315,"Popularity":87,"Themes":"mate mateIn1 oneMove opening","OpeningFamily":"","Opening":"","OpeningVariation":"","ECO":"","OpeningTags":"Center_Game Center_Game_Halasz-McDonnell_Gambit"},{"PuzzleId":"9krWy","Fen":"3rrkn1/ppq2ppQ/2n2b2/2p1P3/3p4/1P1B3P/P1P3P1/RNB1R1K1 w - - 0 17","Moves":"e5f6 e8e1 g1f2 g8f6","Rating":2030,"NbPlays":771,"Popularity":95,"Themes":"crushing fork hangingPiece intermezzo opening short","OpeningFamily":"","Opening":"","OpeningVariation":"","ECO":"","OpeningTags":"Center_Game Center_Game_Halasz-McDonnell_Gambit"},{"PuzzleId":"zSUnr","Fen":"rnb1kb1r/pp1pqNp1/7p/2p5/2BpnP2/8/PPP3PP/RNBQK2R w KQkq - 1 8","Moves":"f7h8 e4c3 c4e2 c3d1","Rating":1730,"NbPlays":2228,"Popularity":94,"Themes":"advantage discoveredAttack opening pin short","OpeningFamily":"","Opening":"","OpeningVariation":"","ECO":"","OpeningTags":"Center_Game Center_Game_Halasz-McDonnell_Gambit"},{"PuzzleId":"1BP1M","Fen":"rn1qk2r/ppp2ppp/4b3/2bnP3/2BN4/8/PPP3PP/RNBQK2R w KQkq - 1 9","Moves":"d4e6 d8h4 g2g3 h4e4 d1e2 e4h1","Rating":2052,"NbPlays":8113,"Popularity":93,"Themes":"crushing exposedKing fork long opening","OpeningFamily":"","Opening":"","OpeningVariation":"","ECO":"","OpeningTags":"Center_Game Center_Game_Halasz-McDonnell_Gambit"},{"PuzzleId":"lHmKf","Fen":"r1bq1r2/pppp1p2/2n3pk/2bnP1N1/3p1P2/7Q/PPP3PP/RNB2RK1 b - - 1 11","Moves":"h6g7 h3h7","Rating":923,"NbPlays":20,"Popularity":47,"Themes":"mate mateIn1 oneMove opening","OpeningFamily":"","Opening":"","OpeningVariation":"","ECO":"","OpeningTags":"Center_Game Center_Game_Halasz-McDonnell_Gambit"},{"PuzzleId":"IrS6j","Fen":"rn1q1rk1/ppp1b1pp/4N3/3p3b/5P2/3P2Q1/PP4PP/RNB2RK1 b - - 4 13","Moves":"d8d6 g3g7","Rating":615,"NbPlays":131,"Popularity":100,"Themes":"kingsideAttack mate mateIn1 oneMove opening","OpeningFamily":"","Opening":"","OpeningVariation":"","ECO":"","OpeningTags":"Center_Game Center_Game_Halasz-McDonnell_Gambit"},{"PuzzleId":"P8JM1","Fen":"r1bqk2r/ppp1nppp/2n5/2b3N1/2BpQP2/8/PPP3PP/RNB1K2R b KQkq - 3 9","Moves":"e8g8 e4h7","Rating":984,"NbPlays":65,"Popularity":58,"Themes":"kingsideAttack mate mateIn1 oneMove opening","OpeningFamily":"","Opening":"","OpeningVariation":"","ECO":"","OpeningTags":"Center_Game Center_Game_Halasz-McDonnell_Gambit"},{"PuzzleId":"RZSHw","Fen":"r1bq1rk1/ppp2ppp/2n5/2bnP1N1/3p4/3B4/PPP3PP/RNB1QRK1 b - - 2 10","Moves":"h7h6 e1e4 g7g6 g5f7","Rating":2108,"NbPlays":283,"Popularity":86,"Themes":"crushing opening short","OpeningFamily":"","Opening":"","OpeningVariation":"","ECO":"","OpeningTags":"Center_Game Center_Game_Halasz-McDonnell_Gambit"},{"PuzzleId":"qamJW","Fen":"r2q1rk1/ppp2pp1/2n5/2bpPbNQ/3p1PP1/7P/PPP5/RNB2K2 b - - 0 14","Moves":"f5h7 h5h7","Rating":785,"NbPlays":71,"Popularity":100,"Themes":"kingsideAttack mate mateIn1 oneMove opening","OpeningFamily":"","Opening":"","OpeningVariation":"","ECO":"","OpeningTags":"Center_Game Center_Game_Halasz-McDonnell_Gambit"},{"PuzzleId":"tRVGR","Fen":"r1bq1rk1/ppp2pp1/2n5/2bnP1NQ/3p4/7P/PPP3P1/RNB2RK1 b - - 3 12","Moves":"f7f5 h5h7","Rating":789,"NbPlays":534,"Popularity":92,"Themes":"mate mateIn1 oneMove opening","OpeningFamily":"","Opening":"","OpeningVariation":"","ECO":"","OpeningTags":"Center_Game Center_Game_Halasz-McDonnell_Gambit"},{"PuzzleId":"RlGyf","Fen":"r1bqrk1Q/pppp2p1/2n5/2bnP1N1/3p1P2/8/PPP3PP/RNB2RK1 b - - 6 14","Moves":"f8e7 h8g7","Rating":853,"NbPlays":258,"Popularity":100,"Themes":"mate mateIn1 oneMove opening","OpeningFamily":"","Opening":"","OpeningVariation":"","ECO":"","OpeningTags":"Center_Game Center_Game_Halasz-McDonnell_Gambit"},{"PuzzleId":"isM96","Fen":"r2qk2r/p1pbbppp/8/3n4/5P2/2Q2N2/PPP3PP/RNB1K2R w KQkq - 3 11","Moves":"c3a5 e7b4 a5b4 d5b4","Rating":1002,"NbPlays":351,"Popularity":93,"Themes":"crushing fork opening short","OpeningFamily":"","Opening":"","OpeningVariation":"","ECO":"","OpeningTags":"Center_Game Center_Game_Halasz-McDonnell_Gambit"},{"PuzzleId":"eSuNZ","Fen":"r2qk2r/ppp2ppp/2n2n2/2b1P3/3p2b1/3B1N2/PPP3PP/RNBQ1R1K b kq - 0 9","Moves":"c6e5 d1e1 g4f3 e1e5 d8e7 e5e7","Rating":2261,"NbPlays":35,"Popularity":98,"Themes":"advantage fork long opening pin","OpeningFamily":"","Opening":"","OpeningVariation":"","ECO":"","OpeningTags":"Center_Game Center_Game_Halasz-McDonnell_Gambit"},{"PuzzleId":"bsEOK","Fen":"r2q1rk1/pp2bppp/2n2P2/2p5/7Q/P1N2b2/1P4PP/RBB2RK1 b - - 0 15","Moves":"e7f6 h4h7","Rating":641,"NbPlays":200,"Popularity":87,"Themes":"kingsideAttack mate mateIn1 oneMove opening","OpeningFamily":"","Opening":"","OpeningVariation":"","ECO":"","OpeningTags":"Center_Game Center_Game_Halasz-McDonnell_Gambit"},{"PuzzleId":"YvuPh","Fen":"r1bqr1k1/ppp2ppp/2n5/3n4/2BP1P2/3Q1N2/P5PP/R1B2RK1 b - - 1 14","Moves":"g8h8 f3g5 d8g5 f4g5","Rating":1493,"NbPlays":273,"Popularity":86,"Themes":"crushing opening short","OpeningFamily":"","Opening":"","OpeningVariation":"","ECO":"","OpeningTags":"Center_Game Center_Game_Halasz-McDonnell_Gambit"},{"PuzzleId":"RUffq","Fen":"r1bq1rk1/pppp1pp1/2n5/2bnP1NQ/5P2/3p4/PPP3PP/RNB2R1K b - - 1 11","Moves":"f7f6 h5h7","Rating":810,"NbPlays":242,"Popularity":97,"Themes":"mate mateIn1 oneMove opening","OpeningFamily":"","Opening":"","OpeningVariation":"","ECO":"","OpeningTags":"Center_Game Center_Game_Halasz-McDonnell_Gambit"},{"PuzzleId":"YP0cl","Fen":"r2q1rk1/ppp1npp1/2n5/2b1PbNQ/8/P1N5/1Pp3PP/R1B2R1K b - - 1 14","Moves":"c6e5 f1f5 d8d1 c3d1 c2d1q h5d1","Rating":1603,"NbPlays":2315,"Popularity":97,"Themes":"advantage long opening","OpeningFamily":"","Opening":"","OpeningVariation":"","ECO":"","OpeningTags":"Center_Game Center_Game_Halasz-McDonnell_Gambit"},{"PuzzleId":"uYOv6","Fen":"r2qk2r/2ppnppp/bp6/pNb1P3/2P2P2/3Q4/P5PP/RNB2R1K b kq - 2 14","Moves":"c7c6 b5d6 c5d6 e5d6","Rating":1556,"NbPlays":10026,"Popularity":93,"Themes":"advantage opening short","OpeningFamily":"","Opening":"","OpeningVariation":"","ECO":"","OpeningTags":"Center_Game Center_Game_Halasz-McDonnell_Gambit"},{"PuzzleId":"ewzkH","Fen":"r1bq1r1k/pppp1Bp1/2n3Qp/4P1N1/5P2/3p4/PPP2bPP/RNB4K b - - 2 13","Moves":"h6g5 g6h5","Rating":1209,"NbPlays":156,"Popularity":89,"Themes":"mate mateIn1 oneMove opening","OpeningFamily":"","Opening":"","OpeningVariation":"","ECO":"","OpeningTags":"Center_Game Center_Game_Halasz-McDonnell_Gambit"},{"PuzzleId":"rcan5","Fen":"rnb2rk1/ppp2ppp/3p4/8/1b1NPPn1/3B2Pq/PPPNQ2P/R1B1K2R w KQ - 3 10","Moves":"b2b3 b4c3 d4b5 c3a1","Rating":1702,"NbPlays":237,"Popularity":75,"Themes":"crushing fork opening short","OpeningFamily":"","Opening":"","OpeningVariation":"","ECO":"","OpeningTags":"Center_Game Center_Game_Halasz-McDonnell_Gambit"},{"PuzzleId":"mSbmq","Fen":"r1bq1r2/pppp1pp1/2n4k/2bnP1N1/3p1P2/3Q4/PPP3PP/RNB2RK1 b - - 3 10","Moves":"g7g6 d3h3 h6g7 h3h7","Rating":1193,"NbPlays":821,"Popularity":99,"Themes":"mate mateIn2 opening short","OpeningFamily":"","Opening":"","OpeningVariation":"","ECO":"","OpeningTags":"Center_Game Center_Game_Halasz-McDonnell_Gambit"},{"PuzzleId":"JTAsA","Fen":"r2qk1nr/pp2b1pp/2n5/2ppP3/3p2b1/1P1B1N2/P1PN2PP/R1BQ1RK1 b kq - 0 10","Moves":"c6e5 f3e5 g4d1 d3b5","Rating":2059,"NbPlays":220,"Popularity":83,"Themes":"crushing opening sacrifice short","OpeningFamily":"","Opening":"","OpeningVariation":"","ECO":"","OpeningTags":"Center_Game Center_Game_Halasz-McDonnell_Gambit"}]