[{"PuzzleId":"xajTh","Fen":"r1b2rk1/pp3ppp/2p5/2Pp4/1P4nq/P1NBP3/3B1PP1/R2Q1RK1 w - - 3 16","Moves":"f2f3 h4h2","Rating":836,"NbPlays":102,"Popularity":67,"Themes":"mate mateIn1 oneMove opening","OpeningFamily":"","Opening":"","OpeningVariation":"","ECO":"","OpeningTags":"Semi-Slav_Defense Semi-Slav_Defense_Main_Line"},{"PuzzleId":"Nf7dh","Fen":"rn1q1rk1/pp3ppp/5n2/3p1b2/3P4/P2BPN2/5PPP/R1BQK2R b KQ - 1 11","Moves":"d8a5 c1d2 f5d3 d2a5","Rating":986,"NbPlays":70,"Popularity":75,"Themes":"advantage defensiveMove opening short","OpeningFamily":"","Opening":"","OpeningVariation":"","ECO":"","OpeningTags":"Semi-Slav_Defense Semi-Slav_Defense_Main_Line"},{"PuzzleId":"g5P1a","Fen":"r1b2rk1/ppbn1ppp/3q1n2/3P4/3Pp3/2N4P/PPBN1PP1/R1BQ1RK1 w - - 2 14","Moves":"d2e4 d6h2","Rating":684,"NbPlays":166,"Popularity":85,"Themes":"mate mateIn1 oneMove opening","OpeningFamily":"","Opening":"","OpeningVariation":"","ECO":"","OpeningTags":"Semi-Slav_Defense Semi-Slav_Defense_Main_Line"},{"PuzzleId":"jfFfp","Fen":"2rq1rk1/1b1n1pp1/p3p3/1pbnP1NQ/8/P1N5/1P3PPP/R1B2RK1 b - - 3 18","Moves":"f7f6 h5h7","Rating":1125,"NbPlays":74,"Popularity":100,"Themes":"mate mateIn1 oneMove opening","OpeningFamily":"","Opening":"","OpeningVariation":"","ECO":"","OpeningTags":"Semi-Slav_Defense Semi-Slav_Defense_Main_Line"},{"PuzzleId":"xQaHb","Fen":"rbb2rk1/p1q2ppp/n1p2n2/1pPp4/1P1Pp3/P1N1P3/2NBBPPP/R2Q1RK1 w - - 4 16","Moves":"a3a4 c7h2","Rating":400,"NbPlays":523,"Popularity":97,"Themes":"kingsideAttack mate mateIn1 oneMove opening","OpeningFamily":"","Opening":"","OpeningVariation":"","ECO":"","OpeningTags":"Semi-Slav_Defense Semi-Slav_Defense_Main_Line"},{"PuzzleId":"GrAT6","Fen":"rn3rk1/pp2bpp1/2p2n1p/4NB1q/3Pp3/2N5/PPQ2P2/R1B2RK1 w - - 0 15","Moves":"c3e4 h5f5 e4f6 f5f6","Rating":1540,"NbPlays":1369,"Popularity":89,"Themes":"advantage hangingPiece opening short","OpeningFamily":"","Opening":"","OpeningVariation":"","ECO":"","OpeningTags":"Semi-Slav_Defense Semi-Slav_Defense_Main_Line"},{"PuzzleId":"Q86eX","Fen":"r1b2rk1/pp1nq1pp/2pbp3/3p1p2/2PPn3/1PN1PN2/PB2BPPP/R2QR1K1 w - - 0 11","Moves":"f3d2 d6h2 g1h2 e7h4 h2g1 h4f2","Rating":1962,"NbPlays":3655,"Popularity":92,"Themes":"attraction crushing kingsideAttack long master opening sacrifice","OpeningFamily":"","Opening":"","OpeningVariation":"","ECO":"","OpeningTags":"Semi-Slav_Defense Semi-Slav_Defense_Main_Line"},{"PuzzleId":"RlOAt","Fen":"2rq1rk1/ppb2ppp/2p2n2/2Ppn3/PP1N4/2N1P3/5PPP/R1BQ1RK1 b - - 1 13","Moves":"f6g4 f2f4 g4h2 g1h2","Rating":1642,"NbPlays":63,"Popularity":18,"Themes":"advantage opening short","OpeningFamily":"","Opening":"","OpeningVariation":"","ECO":"","OpeningTags":"Semi-Slav_Defense Semi-Slav_Defense_Main_Line"},{"PuzzleId":"hikBU","Fen":"r1b1r1k1/pp3pp1/1nNb3p/8/3PB2q/8/PPQ2PPP/R1B2RK1 w - - 1 16","Moves":"g2g3 h4e4 c2e4 e8e4","Rating":1482,"NbPlays":2134,"Popularity":91,"Themes":"crushing opening short","OpeningFamily":"","Opening":"","OpeningVariation":"","ECO":"","OpeningTags":"Semi-Slav_Defense Semi-Slav_Defense_Main_Line"},{"PuzzleId":"Ok6kl","Fen":"r1bq1rk1/pp1n1ppp/2p1p3/3p4/2PPn3/1P2PN2/P1Q2PPP/R1B1KB1R w KQ - 3 10","Moves":"c1a3 d8a5 b3b4 a5a3","Rating":1118,"NbPlays":295,"Popularity":100,"Themes":"advantage fork opening short","OpeningFamily":"","Opening":"","OpeningVariation":"","ECO":"","OpeningTags":"Semi-Slav_Defense Semi-Slav_Defense_Main_Line"},{"PuzzleId":"DqvxQ","Fen":"1rbq1rk1/p3bppp/p1p2n2/8/3PN3/P4N2/1PQ2PPP/R1B2RK1 b - - 0 12","Moves":"c8f5 e4f6 e7f6 c2f5","Rating":824,"NbPlays":2001,"Popularity":95,"Themes":"crushing discoveredAttack kingsideAttack opening short","OpeningFamily":"","Opening":"","OpeningVariation":"","ECO":"","OpeningTags":"Semi-Slav_Defense Semi-Slav_Defense_Main_Line"},{"PuzzleId":"2Oi9l","Fen":"rnb2r2/4bpk1/p3N3/1p6/6Q1/2pq4/PP3PPP/R1B2RK1 b - - 0 18","Moves":"g7h8 g4g7","Rating":855,"NbPlays":470,"Popularity":95,"Themes":"mate mateIn1 oneMove opening","OpeningFamily":"","Opening":"","OpeningVariation":"","ECO":"","OpeningTags":"Semi-Slav_Defense Semi-Slav_Defense_Main_Line"},{"PuzzleId":"7gZSv","Fen":"rn1q1rk1/1b2bpp1/p3p2p/1p1nP1N1/2pP4/P4N2/1PQ2PPP/RBB2RK1 b - - 1 17","Moves":"h6g5 c2h7","Rating":1162,"NbPlays":24,"Popularity":85,"Themes":"mate mateIn1 oneMove opening","OpeningFamily":"","Opening":"","OpeningVariation":"","ECO":"","OpeningTags":"Semi-Slav_Defense Semi-Slav_Defense_Main_Line"},{"PuzzleId":"e6bkb","Fen":"2rq1rk1/1b1n1p1p/p3p1p1/1pbnP1N1/8/5N2/PPQ1BPPP/R1BR2K1 w - - 0 17","Moves":"g5e4 c5f2 e4f2 c8c2","Rating":1367,"NbPlays":19459,"Popularity":97,"Themes":"crushing discoveredAttack master opening short","OpeningFamily":"","Opening":"","OpeningVariation":"","ECO":"","OpeningTags":"Semi-Slav_Defense Semi-Slav_Defense_Main_Line"},{"PuzzleId":"WpK15","Fen":"r1bq1rk1/pp3ppp/2p2n2/4b3/2B1P3/2N5/PP3PPP/R1BQR1K1 b - - 0 12","Moves":"e5h2 g1h2 f6g4 h2g3","Rating":1942,"NbPlays":79,"Popularity":89,"Themes":"advantage hangingPiece opening short","OpeningFamily":"","Opening":"","OpeningVariation":"","ECO":"","OpeningTags":"Semi-Slav_Defense Semi-Slav_Defense_Main_Line"},{"PuzzleId":"PMYem","Fen":"rn3rk1/ppb2ppp/2pq1n2/1P1p4/P2P4/2NBPb2/5PPP/R1BQ1RK1 w - - 0 13","Moves":"d1f3 d6h2","Rating":400,"NbPlays":377,"Popularity":88,"Themes":"kingsideAttack mate mateIn1 oneMove opening","OpeningFamily":"","Opening":"","OpeningVariation":"","ECO":"","OpeningTags":"Semi-Slav_Defense Semi-Slav_Defense_Main_Line"},{"PuzzleId":"rL4qv","Fen":"r1b2rk1/1pq1bppp/p7/2Ppn3/1P6/5N2/P3BPPP/R1BQ1RK1 w - - 0 14","Moves":"c1f4 e5f3 e2f3 c7f4","Rating":917,"NbPlays":293,"Popularity":91,"Themes":"advantage discoveredAttack kingsideAttack opening short","OpeningFamily":"","Opening":"","OpeningVariation":"","ECO":"","OpeningTags":"Semi-Slav_Defense Semi-Slav_Defense_Main_Line"},{"PuzzleId":"atrJt","Fen":"r1b2rk1/ppb3pp/2p5/2Pp4/1P3Ppq/2N1P3/P2BB1P1/R2Q1RK1 w - - 0 17","Moves":"d1e1 g4g3 e1g3 h4g3","Rating":1238,"NbPlays":870,"Popularity":93,"Themes":"crushing opening short","OpeningFamily":"","Opening":"","OpeningVariation":"","ECO":"","OpeningTags":"Semi-Slav_Defense Semi-Slav_Defense_Main_Line"},{"PuzzleId":"AZkRj","Fen":"r1b1k2r/ppq1bppp/4p3/2p1P3/1nPP3P/5N2/P2B1PP1/RB1Q1RK1 b kq - 0 15","Moves":"c5d4 d2b4 e7b4 d1a4 c8d7 a4b4","Rating":1748,"NbPlays":873,"Popularity":86,"Themes":"crushing fork long opening","OpeningFamily":"","Opening":"","OpeningVariation":"","ECO":"","OpeningTags":"Semi-Slav_Defense Semi-Slav_Defense_Main_Line"},{"PuzzleId":"GapzP","Fen":"r1bq1rk1/4bppp/p3p3/1p1nN3/3PQ3/P2B4/1P3PPP/R1BR2K1 b - - 0 16","Moves":"c8b7 e4h7","Rating":1119,"NbPlays":15,"Popularity":100,"Themes":"kingsideAttack mate mateIn1 oneMove opening","OpeningFamily":"","Opening":"","OpeningVariation":"","ECO":"","OpeningTags":"Semi-Slav_Defense Semi-Slav_Defense_Main_Line"},{"PuzzleId":"SqvNM","Fen":"r1bqr1k1/pp1n1ppB/2pbpn1p/3p2N1/2PP4/2N1P3/PPQ2PPP/R1B2RK1 b - - 1 10","Moves":"g8h8 g5f7","Rating":665,"NbPlays":604,"Popularity":100,"Themes":"kingsideAttack mate mateIn1 oneMove opening","OpeningFamily":"","Opening":"","OpeningVariation":"","ECO":"","OpeningTags":"Semi-Slav_Defense Semi-Slav_Defense_Main_Line"},{"PuzzleId":"8XLlw","Fen":"r1bq1rk1/pp3ppn/2p1p2p/4P3/2Pp1PPb/2N1P3/PPQ4P/R1BK1BR1 w - - 0 13","Moves":"e3d4 d8d4 c2d3 d4g1","Rating":1258,"NbPlays":95,"Popularity":85,"Themes":"crushing fork opening short","OpeningFamily":"","Opening":"","OpeningVariation":"","ECO":"","OpeningTags":"Semi-Slav_Defense Semi-Slav_Defense_Main_Line"},{"PuzzleId":"njY9v","Fen":"r2q1rk1/1b3pp1/p4n1p/1p1pb3/8/1PNQP3/PB3PPP/1BRR2K1 b - - 1 17","Moves":"f6e4 c3e4 d5e4 d3d8","Rating":1403,"NbPlays":1933,"Popularity":93,"Themes":"crushing opening short","OpeningFamily":"","Opening":"","OpeningVariation":"","ECO":"","OpeningTags":"Semi-Slav_Defense Semi-Slav_Defense_Main_Line"},{"PuzzleId":"I94EU","Fen":"rn1q1rk1/3n1ppp/b1p1p3/p3N3/1pPP4/3QP3/P1B2PPP/R1B2RK1 b - - 2 14","Moves":"d7e5 d3h7","Rating":582,"NbPlays":1082,"Popularity":93,"Themes":"kingsideAttack mate mateIn1 oneMove opening","OpeningFamily":"","Opening":"","OpeningVariation":"","ECO":"","OpeningTags":"Semi-Slav_Defense Semi-Slav_Defense_Main_Line"},{"PuzzleId":"T46o4","Fen":"rn1q1rk1/pb3ppp/4pn2/1B2N3/3p4/2P1P3/P4PPP/R1BQ1RK1 w - - 0 13","Moves":"c3d4 d8d5 f2f3 d5b5","Rating":1553,"NbPlays":2039,"Popularity":91,"Themes":"advantage opening short","OpeningFamily":"","Opening":"","OpeningVariation":"","ECO":"","OpeningTags":"Semi-Slav_Defense Semi-Slav_Defense_Main_Line"},{"PuzzleId":"E2c5v","Fen":"rnbq1rk1/1p3ppp/p2bp3/3n4/3PN3/P2B1N2/1PQ2PPP/R1B2RK1 b - - 2 12","Moves":"d8c7 e4d6 c7c2 d3c2","Rating":1575,"NbPlays":1259,"Popularity":91,"Themes":"crushing opening short","OpeningFamily":"","Opening":"","OpeningVariation":"","ECO":"","OpeningTags":"Semi-Slav_Defense Semi-Slav_Defense_Main_Line"},{"PuzzleId":"HbDw2","Fen":"rnbqr1k1/pp3pp1/2pb1n1p/8/3PN3/3B1N2/PP3PPP/R1BQR1K1 b - - 0 11","Moves":"f6d5 e4d6 e8e1 d1e1","Rating":1314,"NbPlays":1144,"Popularity":91,"Themes":"crushing opening short","OpeningFamily":"","Opening":"","OpeningVariation":"","ECO":"","OpeningTags":"Semi-Slav_Defense Semi-Slav_Defense_Main_Line"},{"PuzzleId":"MUNH6","Fen":"r1b1k2r/pp1nqpp1/2p5/2Pp3p/1P1Pp1n1/P1N1PP2/3NB1PK/R1BQ1R2 w kq - 1 14","Moves":"f3g4 h5g4 h2g1 h8h1 g1h1 e7h4 h1g1 g4g3 d2f3 e4f3 f1f3 h4h2 g1f1 h2h1","Rating":2368,"NbPlays":137,"Popularity":85,"Themes":"attraction discoveredAttack mate mateIn5 opening sacrifice veryLong","OpeningFamily":"","Opening":"","OpeningVariation":"","ECO":"","OpeningTags":"Semi-Slav_Defense Semi-Slav_Defense_Main_Line"},{"PuzzleId":"S6C4w","Fen":"r2q1rk1/p1nnbppp/bp2p3/3pP3/3P4/5N2/PPQ1NPPP/RBB2RK1 b - - 5 13","Moves":"a8c8 c2h7","Rating":523,"NbPlays":475,"Popularity":97,"Themes":"kingsideAttack master mate mateIn1 oneMove opening","OpeningFamily":"","Opening":"","OpeningVariation":"","ECO":"","OpeningTags":"Semi-Slav_Defense Semi-Slav_Defense_Main_Line"},{"PuzzleId":"muta2","Fen":"r1b1k2r/2q1bppp/p1p1p3/1pPnN3/P2PR3/8/5PPP/RBBQ2K1 b kq - 0 18","Moves":"f7f6 d1h5 g7g6 e5g6 h7g6 h5h8","Rating":1188,"NbPlays":232,"Popularity":86,"Themes":"crushing long opening","OpeningFamily":"","Opening":"","OpeningVariation":"","ECO":"","OpeningTags":"Semi-Slav_Defense Semi-Slav_Defense_Main_Line"},{"PuzzleId":"3sqjN","Fen":"1r1bbrk1/1pq2pp1/pNp1pn1p/P1Pp4/3PP3/6P1/1P1BBP1P/R2Q1RK1 b - - 0 17","Moves":"f6e4 d2f4 c7f4 g3f4","Rating":1543,"NbPlays":1058,"Popularity":88,"Themes":"advantage opening short","OpeningFamily":"","Opening":"","OpeningVariation":"","ECO":"","OpeningTags":"Semi-Slav_Defense Semi-Slav_Defense_Main_Line"},{"PuzzleId":"ADefv","Fen":"r1b2rk1/p1qn1ppp/2p2n2/2Ppp3/1P6/2BBPN2/P4PPP/R2QR1K1 w - - 0 14","Moves":"c3e5 d7e5 f3e5 c7e5","Rating":1067,"NbPlays":40,"Popularity":67,"Themes":"advantage opening short","OpeningFamily":"","Opening":"","OpeningVariation":"","ECO":"","OpeningTags":"Semi-Slav_Defense Semi-Slav_Defense_Main_Line"},{"PuzzleId":"0LsB9","Fen":"r1bq1rk1/pp3ppp/2p2n2/4b3/2B5/1PN1P3/PB3PPP/R2Q1RK1 b - - 1 12","Moves":"e5h2 g1h2 f6g4 h2g1","Rating":1499,"NbPlays":13901,"Popularity":94,"Themes":"advantage defensiveMove hangingPiece opening short","OpeningFamily":"","Opening":"","OpeningVariation":"","ECO":"","OpeningTags":"Semi-Slav_Defense Semi-Slav_Defense_Main_Line"},{"PuzzleId":"aOaUP","Fen":"r1bqr1k1/pp3pbp/6p1/2pn4/4B3/P4N2/1PQ2PPP/R1BR2K1 b - - 1 16","Moves":"c8e6 e4d5 e6d5 c2c5 d5c6 d1d8","Rating":2173,"NbPlays":1065,"Popularity":91,"Themes":"advantage long opening","OpeningFamily":"","Opening":"","OpeningVariation":"","ECO":"","OpeningTags":"Semi-Slav_Defense Semi-Slav_Defense_Main_Line"},{"PuzzleId":"4YsrE","Fen":"r1bqk2r/pp3ppp/1n2pn2/3p4/1b1P4/2N1PNP1/PP1B1PBP/R2QK2R b KQkq - 1 9","Moves":"b6c4 d1a4 c8d7 a4b4 a7a5 b4b3","Rating":1779,"NbPlays":71,"Popularity":83,"Themes":"crushing fork long opening","OpeningFamily":"","Opening":"","OpeningVariation":"","ECO":"","OpeningTags":"Semi-Slav_Defense Semi-Slav_Defense_Main_Line"},{"PuzzleId":"EdUYe","Fen":"r1bqrbk1/pp3ppp/2p2n2/2P1p1N1/3PB3/P7/1PQ2PPP/R1B2RK1 b - - 3 14","Moves":"h7h6 e4h7 f6h7 c2h7","Rating":1188,"NbPlays":220,"Popularity":83,"Themes":"kingsideAttack mate mateIn2 opening short","OpeningFamily":"","Opening":"","OpeningVariation":"","ECO":"","OpeningTags":"Semi-Slav_Defense Semi-Slav_Defense_Main_Line"},{"PuzzleId":"7nlYq","Fen":"r1bqk2r/pp2bppp/2n1p3/3pN3/3P4/4P3/PP3PPP/R1BQKB1R w KQkq - 2 9","Moves":"f1b5 d8a5 c1d2 a5b5","Rating":1285,"NbPlays":19,"Popularity":86,"Themes":"crushing fork opening short","OpeningFamily":"","Opening":"","OpeningVariation":"","ECO":"","OpeningTags":"Semi-Slav_Defense Semi-Slav_Defense_Main_Line"},{"PuzzleId":"h4oTw","Fen":"r2q2kr/pb2b1p1/1pp3Bp/3nPQ2/8/8/PP3PPP/R1B2RK1 b - - 4 17","Moves":"e7f6 f5e6 g8f8 e6f7","Rating":1141,"NbPlays":774,"Popularity":93,"Themes":"kingsideAttack mate mateIn2 opening short","OpeningFamily":"","Opening":"","OpeningVariation":"","ECO":"","OpeningTags":"Semi-Slav_Defense Semi-Slav_Defense_Main_Line"},{"PuzzleId":"DCUtB","Fen":"r1b1r1k1/pp1nq1b1/2p1pnQ1/3p4/2PPP3/2N2N2/PP3PP1/R1B1K2R b KQ - 0 13","Moves":"e7f7 h1h8 g8h8 g6f7","Rating":1755,"NbPlays":17,"Popularity":87,"Themes":"crushing deflection kingsideAttack opening pin short","OpeningFamily":"","Opening":"","OpeningVariation":"","ECO":"","OpeningTags":"Semi-Slav_Defense Semi-Slav_Defense_Main_Line"},{"PuzzleId":"KbQ78","Fen":"r2qnrk1/1b2bpp1/1p2p2p/2npP3/8/P1N2N1P/1PQ2PP1/RBB2RK1 b - - 1 16","Moves":"a8c8 c2h7","Rating":420,"NbPlays":493,"Popularity":84,"Themes":"mate mateIn1 oneMove opening","OpeningFamily":"","Opening":"","OpeningVariation":"","ECO":"","OpeningTags":"Semi-Slav_Defense Semi-Slav_Defense_Main_Line"},{"PuzzleId":"P96qx","Fen":"r2qr1k1/pp2bppp/2p2n2/8/3P2b1/3Q1N2/PPB2PPP/R1B1R1K1 b - - 4 14","Moves":"e7b4 e1e8 d8e8 c1g5","Rating":1926,"NbPlays":1918,"Popularity":92,"Themes":"crushing kingsideAttack opening short","OpeningFamily":"","Opening":"","OpeningVariation":"","ECO":"","OpeningTags":"Semi-Slav_Defense Semi-Slav_Defense_Main_Line"},{"PuzzleId":"mtKAo","Fen":"rn1qk2r/p3bppp/1p2pn2/1N1p4/3P4/4PN2/PPQ2PPP/R1B2RK1 b kq - 5 11","Moves":"a7a6 b5c7 d8c7 c2c7","Rating":1038,"NbPlays":428,"Popularity":90,"Themes":"advantage fork opening short","OpeningFamily":"","Opening":"","OpeningVariation":"","ECO":"","OpeningTags":"Semi-Slav_Defense Semi-Slav_Defense_Main_Line"},{"PuzzleId":"6pd40","Fen":"rbb1k2r/1pq2pp1/1pp1p2p/2Pp2n1/3P4/4PN1P/PQ2BPP1/R1B2RK1 w kq - 0 16","Moves":"c5b6 g5f3 g2f3 c7h2","Rating":1250,"NbPlays":477,"Popularity":89,"Themes":"kingsideAttack mate mateIn2 opening short","OpeningFamily":"","Opening":"","OpeningVariation":"","ECO":"","OpeningTags":"Semi-Slav_Defense Semi-Slav_Defense_Main_Line"},{"PuzzleId":"UCdT9","Fen":"1rb1kb1r/p1qn1ppp/1pB1pn2/3pN3/3P4/2N1P3/PP3PPP/R1BQ1RK1 b k - 7 10","Moves":"f8d6 c3b5 d6e5 b5c7","Rating":1792,"NbPlays":891,"Popularity":92,"Themes":"crushing opening short","OpeningFamily":"","Opening":"","OpeningVariation":"","ECO":"","OpeningTags":"Semi-Slav_Defense Semi-Slav_Defense_Main_Line"},{"PuzzleId":"AwFPn","Fen":"r2q1rk1/pb3ppp/1p2pb2/3n4/3P4/3QBN2/PP3PPP/RB3RK1 b - - 7 15","Moves":"d5e3 d3h7","Rating":1111,"NbPlays":241,"Popularity":81,"Themes":"kingsideAttack mate mateIn1 oneMove opening","OpeningFamily":"","Opening":"","OpeningVariation":"","ECO":"","OpeningTags":"Semi-Slav_Defense Semi-Slav_Defense_Main_Line"},{"PuzzleId":"RZwRv","Fen":"1br2rk1/p1qn1ppp/1pp2nb1/3p4/1P1P3N/P1N1P2P/1B2BPP1/2RQ1RK1 w - - 9 18","Moves":"h4g6 c7h2","Rating":1035,"NbPlays":47,"Popularity":79,"Themes":"mate mateIn1 oneMove opening","OpeningFamily":"","Opening":"","OpeningVariation":"","ECO":"","OpeningTags":"Semi-Slav_Defense Semi-Slav_Defense_Main_Line"},{"PuzzleId":"KJb2p","Fen":"rn3rk1/p1q1bppp/1pp2n2/3p2N1/3P3P/2NQP3/PP3PP1/R1B1R1K1 b - - 0 12","Moves":"f6g4 d3h7","Rating":570,"NbPlays":73,"Popularity":100,"Themes":"kingsideAttack mate mateIn1 oneMove opening","OpeningFamily":"","Opening":"","OpeningVariation":"","ECO":"","OpeningTags":"Semi-Slav_Defense Semi-Slav_Defense_Main_Line"},{"PuzzleId":"WaSmh","Fen":"2bq1rk1/2b2ppB/1p2pn2/2p3NQ/r2P4/8/PP3PPP/R1B1R1K1 b - - 0 16","Moves":"f6h7 h5h7","Rating":673,"NbPlays":82,"Popularity":61,"Themes":"kingsideAttack mate mateIn1 oneMove opening","OpeningFamily":"","Opening":"","OpeningVariation":"","ECO":"","OpeningTags":"Semi-Slav_Defense Semi-Slav_Defense_Main_Line"},{"PuzzleId":"aJ9nr","Fen":"r1bq1rk1/1p1n1ppp/p1pbp3/8/2PPB3/5N2/PP3PPP/R1BQ1RK1 w - - 1 11","Moves":"e4h7 g8h7 f3g5 h7g8","Rating":1212,"NbPlays":191,"Popularity":86,"Themes":"advantage defensiveMove hangingPiece opening short","OpeningFamily":"","Opening":"","OpeningVariation":"","ECO":"","OpeningTags":"Semi-Slav_Defense Semi-Slav_Defense_Main_Line"},{"PuzzleId":"iw1N3","Fen":"1rb2rk1/p4ppp/2p1p3/bp1nP1q1/2p2P2/P1N1P1P1/1P1Q2BP/R1BR2K1 b - - 0 16","Moves":"g5g6 c3d5 e6d5 d2a5","Rating":1918,"NbPlays":316,"Popularity":84,"Themes":"advantage discoveredAttack opening short","OpeningFamily":"","Opening":"","OpeningVariation":"","ECO":"","OpeningTags":"Semi-Slav_Defense Semi-Slav_Defense_Main_Line"},{"PuzzleId":"PcHyJ","Fen":"rq2r1k1/pp1n1pp1/2pb3p/3p4/3Pn3/P1NQPN1P/1P3PP1/2R1BRK1 w - - 1 16","Moves":"c3e4 d5e4 d3d1 e4f3","Rating":1349,"NbPlays":572,"Popularity":79,"Themes":"crushing fork opening short","OpeningFamily":"","Opening":"","OpeningVariation":"","ECO":"","OpeningTags":"Semi-Slav_Defense Semi-Slav_Defense_Main_Line"},{"PuzzleId":"HhVqB","Fen":"r1bqkb1r/pp3ppp/2n1p3/8/3Q4/4PN2/PP3PPP/R1B1KB1R w KQkq - 1 10","Moves":"f1b5 d8a5 f3d2 a5b5","Rating":1453,"NbPlays":31291,"Popularity":95,"Themes":"advantage fork opening short","OpeningFamily":"","Opening":"","OpeningVariation":"","ECO":"","OpeningTags":"Semi-Slav_Defense Semi-Slav_Defense_Main_Line"},{"PuzzleId":"OTiHl","Fen":"r1b2rk1/pp3ppp/2p5/2b5/2B1PPn1/P5qP/1PQ3P1/R1BN1R1K w - - 3 18","Moves":"h3g4 g3h4","Rating":1070,"NbPlays":1030,"Popularity":94,"Themes":"mate mateIn1 oneMove opening","OpeningFamily":"","Opening":"","OpeningVariation":"","ECO":"","OpeningTags":"Semi-Slav_Defense Semi-Slav_Defense_Main_Line"},{"PuzzleId":"4aorV","Fen":"r2q1rk1/pb2bppp/1pp1p3/3nP3/3P4/P1PQ1N2/5PPP/RBB2RK1 b - - 4 15","Moves":"d8c8 d3h7","Rating":607,"NbPlays":125,"Popularity":82,"Themes":"kingsideAttack mate mateIn1 oneMove opening","OpeningFamily":"","Opening":"","OpeningVariation":"","ECO":"","OpeningTags":"Semi-Slav_Defense Semi-Slav_Defense_Main_Line"},{"PuzzleId":"ro1dH","Fen":"r1b1k2r/2B2ppp/1q2pn2/pp6/4n3/P3PN2/1P2BPPP/2RQK2R b Kkq - 3 16","Moves":"b6b7 d1d8","Rating":749,"NbPlays":115,"Popularity":71,"Themes":"mate mateIn1 oneMove opening","OpeningFamily":"","Opening":"","OpeningVariation":"","ECO":"","OpeningTags":"Semi-Slav_Defense Semi-Slav_Defense_Main_Line"},{"PuzzleId":"MTh9E","Fen":"r1bq1rk1/ppb2ppp/2p2n2/2Ppn3/1P6/2N1PN2/PB2BPPP/R2Q1RK1 b - - 3 11","Moves":"c8g4 f3e5 c7e5 e2g4","Rating":1095,"NbPlays":2422,"Popularity":97,"Themes":"crushing discoveredAttack master opening short","OpeningFamily":"","Opening":"","OpeningVariation":"","ECO":"","OpeningTags":"Semi-Slav_Defense Semi-Slav_Defense_Main_Line"},{"PuzzleId":"wSHTC","Fen":"r1bqk2r/pp3pp1/2n2n1p/3p4/3P4/P3PN2/5PPP/R1BQKB1R w KQkq - 0 11","Moves":"f1b5 d8a5 c1d2 a5b5","Rating":1057,"NbPlays":388,"Popularity":94,"Themes":"advantage fork opening short","OpeningFamily":"","Opening":"","OpeningVariation":"","ECO":"","OpeningTags":"Semi-Slav_Defense Semi-Slav_Defense_Main_Line"},{"PuzzleId":"hJoSU","Fen":"r2q1rk1/1b1nbppp/p3p3/1pPnP3/4N3/3B1N2/PP3PPP/R1BQR1K1 b - - 0 14","Moves":"d7c5 e4c5 e7c5 d3h7 g8h7 f3g5 h7g8 d1h5","Rating":2008,"NbPlays":1921,"Popularity":91,"Themes":"advantage attraction clearance discoveredAttack kingsideAttack opening sacrifice veryLong","OpeningFamily":"","Opening":"","OpeningVariation":"","ECO":"","OpeningTags":"Semi-Slav_Defense Semi-Slav_Defense_Main_Line"},{"PuzzleId":"0Wsc0","Fen":"rn2r1k1/pp3pp1/2pb3p/3p4/3P2n1/1PNBPN1q/P2B1P2/R2QR1K1 w - - 2 17","Moves":"d3f1 d6h2 f3h2 h3h2","Rating":1214,"NbPlays":78,"Popularity":100,"Themes":"kingsideAttack mate mateIn2 opening short","OpeningFamily":"","Opening":"","OpeningVariation":"","ECO":"","OpeningTags":"Semi-Slav_Defense Semi-Slav_Defense_Main_Line"},{"PuzzleId":"CniEW","Fen":"r1bqrbk1/pp1n1ppp/2p1pn2/3p2N1/2PP4/P1NBP3/1PQ2PPP/R1B2RK1 b - - 8 10","Moves":"h7h6 d3h7 f6h7 c2h7","Rating":996,"NbPlays":333,"Popularity":91,"Themes":"kingsideAttack mate mateIn2 opening short","OpeningFamily":"","Opening":"","OpeningVariation":"","ECO":"","OpeningTags":"Semi-Slav_Defense Semi-Slav_Defense_Main_Line"},{"PuzzleId":"H9lZa","Fen":"rnbqkb1r/pp3ppp/2p1p3/4N3/2PPp3/4P3/PP3PPP/R1BQKB1R b KQkq - 1 7","Moves":"f7f6 d1h5 g7g6 e5g6 h7g6 h5h8","Rating":1272,"NbPlays":18940,"Popularity":96,"Themes":"crushing long opening","OpeningFamily":"","Opening":"","OpeningVariation":"","ECO":"","OpeningTags":"Semi-Slav_Defense Semi-Slav_Defense_Main_Line"},{"PuzzleId":"5YLwW","Fen":"r1b2rk1/pp3pp1/3b1n1p/3pq3/8/1PNBP2P/PB3PP1/1R1Q1RK1 w - - 2 15","Moves":"c3d5 e5h2","Rating":973,"NbPlays":443,"Popularity":88,"Themes":"mate mateIn1 oneMove opening","OpeningFamily":"","Opening":"","OpeningVariation":"","ECO":"","OpeningTags":"Semi-Slav_Defense Semi-Slav_Defense_Main_Line"},{"PuzzleId":"2OyyH","Fen":"r1bq1rk1/1p2bppp/2p1pn2/p7/2PPB3/1P3N2/P4PPP/R1BQ1RK1 w - - 1 12","Moves":"c1g5 f6e4 g5e7 d8e7","Rating":1361,"NbPlays":25,"Popularity":75,"Themes":"crushing hangingPiece opening short","OpeningFamily":"","Opening":"","OpeningVariation":"","ECO":"","OpeningTags":"Semi-Slav_Defense Semi-Slav_Defense_Main_Line"},{"PuzzleId":"BghGI","Fen":"r1b1k2r/ppb2ppp/2pqp3/3p2n1/NP6/P3PN1P/1B2BPP1/R2Q1RK1 w kq - 3 15","Moves":"b2e5 g5f3 e2f3 d6e5","Rating":1070,"NbPlays":294,"Popularity":100,"Themes":"advantage kingsideAttack opening short","OpeningFamily":"","Opening":"","OpeningVariation":"","ECO":"","OpeningTags":"Semi-Slav_Defense Semi-Slav_Defense_Main_Line"},{"PuzzleId":"oTvqI","Fen":"r2q1rk1/1b1nbppp/8/pp1p4/2pP4/P1B1PN2/1PQ2PPP/1BR1R1K1 b - - 1 16","Moves":"b5b4 c2h7","Rating":548,"NbPlays":1167,"Popularity":96,"Themes":"kingsideAttack mate mateIn1 oneMove opening","OpeningFamily":"","Opening":"","OpeningVariation":"","ECO":"","OpeningTags":"Semi-Slav_Defense Semi-Slav_Defense_Main_Line"},{"PuzzleId":"mvuIk","Fen":"rn1qk2r/1p1bbpp1/p1p1pnBp/3pN3/2PP4/2N1P3/PPQ2PPP/R1B1K2R b KQkq - 1 9","Moves":"f7g6 c2g6 e8f8 g6f7","Rating":1120,"NbPlays":358,"Popularity":98,"Themes":"master mate mateIn2 opening short","OpeningFamily":"","Opening":"","OpeningVariation":"","ECO":"","OpeningTags":"Semi-Slav_Defense Semi-Slav_Defense_Main_Line"},{"PuzzleId":"k4LTj","Fen":"r1bq1r2/3nbppk/ppp1pN2/3nP3/3P4/5N2/PPQ2PPP/R1B2RK1 b - - 1 14","Moves":"h7h8 c2h7","Rating":613,"NbPlays":143,"Popularity":89,"Themes":"mate mateIn1 oneMove opening","OpeningFamily":"","Opening":"","OpeningVariation":"","ECO":"","OpeningTags":"Semi-Slav_Defense Semi-Slav_Defense_Main_Line"},{"PuzzleId":"UIj8l","Fen":"3rrnk1/pbq2ppp/1p2pb2/4N3/2PB2Q1/1P6/P4PPP/1BR1R1K1 w - - 1 19","Moves":"c1d1 d8d4 g4d4 e8d8 d4e3 d8d1","Rating":2122,"NbPlays":823,"Popularity":85,"Themes":"clearance crushing long opening sacrifice","OpeningFamily":"","Opening":"","OpeningVariation":"","ECO":"","OpeningTags":"Semi-Slav_Defense Semi-Slav_Defense_Main_Line"},{"PuzzleId":"zRGcD","Fen":"r1b2rk1/ppqnbpp1/2p1pn1B/8/2PPN2P/5N2/PPQ2P2/2KR1B1R b - - 0 14","Moves":"g7h6 h1g1 g8h8 c2d2","Rating":2269,"NbPlays":3932,"Popularity":89,"Themes":"crushing opening short","OpeningFamily":"","Opening":"","OpeningVariation":"","ECO":"","OpeningTags":"Semi-Slav_Defense Semi-Slav_Defense_Main_Line"},{"PuzzleId":"dwm1o","Fen":"r1bqr1k1/pp1n1ppp/2p2n2/b1Ppp3/3P4/P1NBPN2/1P1B1PPP/R2Q1RK1 w - - 0 11","Moves":"c3e2 e5e4 d2a5 d8a5","Rating":1521,"NbPlays":1994,"Popularity":94,"Themes":"crushing fork opening short","OpeningFamily":"","Opening":"","OpeningVariation":"","ECO":"","OpeningTags":"Semi-Slav_Defense Semi-Slav_Defense_Main_Line"},{"PuzzleId":"MKtrp","Fen":"rnb2rk1/4bpp1/1q2pn1p/p2pN3/3P4/1PNB4/P4PPP/R1BQK2R b KQ - 0 13","Moves":"b6d4 d3h7 g8h7 d1d4","Rating":1016,"NbPlays":4269,"Popularity":93,"Themes":"advantage discoveredAttack opening short","OpeningFamily":"","Opening":"","OpeningVariation":"","ECO":"","OpeningTags":"Semi-Slav_Defense Semi-Slav_Defense_Main_Line"},{"PuzzleId":"Ly9wD","Fen":"rn1q1rk1/pp1bbppp/4pn2/1N1p4/3P4/4PN2/PP2BPPP/R1BQK2R w KQ - 6 10","Moves":"f3e5 d7b5 e2b5 d8a5 c1d2 a5b5","Rating":1777,"NbPlays":61,"Popularity":86,"Themes":"crushing fork long opening","OpeningFamily":"","Opening":"","OpeningVariation":"","ECO":"","OpeningTags":"Semi-Slav_Defense Semi-Slav_Defense_Main_Line"},{"PuzzleId":"sd9oS","Fen":"r1b2rk1/pp3ppp/2pb1n2/3pq3/2P5/P1N1P3/1PQ1BPPP/R1B2RK1 w - - 0 12","Moves":"c4d5 e5h2","Rating":514,"NbPlays":341,"Popularity":84,"Themes":"kingsideAttack mate mateIn1 oneMove opening","OpeningFamily":"","Opening":"","OpeningVariation":"","ECO":"","OpeningTags":"Semi-Slav_Defense Semi-Slav_Defense_Main_Line"},{"PuzzleId":"3KvLK","Fen":"r2qkb1r/1b2n1pp/2n1Q3/1N2P3/8/8/PP3PPP/R1B2RK1 b kq - 0 16","Moves":"d8d7 b5d6 e8d8 e6b3","Rating":2748,"NbPlays":749,"Popularity":89,"Themes":"advantage opening short","OpeningFamily":"","Opening":"","OpeningVariation":"","ECO":"","OpeningTags":"Semi-Slav_Defense Semi-Slav_Defense_Main_Line"},{"PuzzleId":"uRuIY","Fen":"r1b1k2r/pp3ppp/2pb1n2/3pq3/2P5/2NBP3/PPQ2PPP/R1B2RK1 w kq - 0 11","Moves":"c4d5 e5h2","Rating":742,"NbPlays":183,"Popularity":84,"Themes":"kingsideAttack mate mateIn1 oneMove opening","OpeningFamily":"","Opening":"","OpeningVariation":"","ECO":"","OpeningTags":"Semi-Slav_Defense Semi-Slav_Defense_Main_Line"},{"PuzzleId":"Ef81v","Fen":"r1bq1rk1/2bn1ppp/2p1p3/ppP1P3/1P1P4/P1NQ1N2/5PPP/1RB1K2R b K - 1 16","Moves":"a5b4 f3g5 f7f5 d3h3 d8g5 c1g5","Rating":2368,"NbPlays":449,"Popularity":86,"Themes":"advantage clearance long opening","OpeningFamily":"","Opening":"","OpeningVariation":"","ECO":"","OpeningTags":"Semi-Slav_Defense Semi-Slav_Defense_Main_Line"},{"PuzzleId":"2b2Gs","Fen":"r1bqk2r/p1bn2pp/1pp5/5p2/1PPP4/P4N2/5PPP/R1BQR1K1 b kq - 1 14","Moves":"e8f7 f3g5 f7g8 g5e6","Rating":2087,"NbPlays":160,"Popularity":82,"Themes":"advantage opening short","OpeningFamily":"","Opening":"","OpeningVariation":"","ECO":"","OpeningTags":"Semi-Slav_Defense Semi-Slav_Defense_Main_Line"},{"PuzzleId":"7JRWv","Fen":"rn1q1rk1/pb2bppp/4p3/1ppnN1P1/3P4/2NBP3/PP3P1P/R1BQK1R1 b Q - 2 12","Moves":"c5d4 d1h5 g7g6 e5g6 f7g6 d3g6","Rating":2452,"NbPlays":740,"Popularity":87,"Themes":"crushing long opening","OpeningFamily":"","Opening":"","OpeningVariation":"","ECO":"","OpeningTags":"Semi-Slav_Defense Semi-Slav_Defense_Main_Line"},{"PuzzleId":"sKk5U","Fen":"rn1q1rk1/pb3ppp/4pb2/1p2P3/2pP4/2P2N2/PBQ2PPP/RB3RK1 b - - 0 15","Moves":"b7f3 c2h7","Rating":479,"NbPlays":251,"Popularity":95,"Themes":"kingsideAttack mate mateIn1 oneMove opening","OpeningFamily":"","Opening":"","OpeningVariation":"","ECO":"","OpeningTags":"Semi-Slav_Defense Semi-Slav_Defense_Main_Line"},{"PuzzleId":"MMslB","Fen":"r2q1rk1/1p2bp2/pn2p1pp/1b2N3/3PQ3/4P2P/P1B2PP1/R1B2RK1 b - - 3 18","Moves":"e7f6 e5g6 f7g6 e4g6","Rating":1797,"NbPlays":37,"Popularity":39,"Themes":"crushing kingsideAttack opening short","OpeningFamily":"","Opening":"","OpeningVariation":"","ECO":"","OpeningTags":"Semi-Slav_Defense Semi-Slav_Defense_Main_Line"},{"PuzzleId":"aXnWs","Fen":"r1bq1rk1/ppb2pp1/n1p1p3/3nP1NQ/3P4/2N5/PP3PPP/R1B2RK1 b - - 3 14","Moves":"f7f6 h5h7","Rating":845,"NbPlays":101,"Popularity":69,"Themes":"opening","OpeningFamily":"","Opening":"","OpeningVariation":"","ECO":"","OpeningTags":"Semi-Slav_Defense Semi-Slav_Defense_Main_Line"},{"PuzzleId":"h6Jz0","Fen":"rnbqk2r/pp3ppp/2p1pn2/8/2PP4/4PN2/P4PPP/R1BQKB1R w KQkq - 1 9","Moves":"c1a3 d8a5 d1d2 a5a3","Rating":1073,"NbPlays":129,"Popularity":65,"Themes":"crushing fork opening short","OpeningFamily":"","Opening":"","OpeningVariation":"","ECO":"","OpeningTags":"Semi-Slav_Defense Semi-Slav_Defense_Main_Line"},{"PuzzleId":"euvwQ","Fen":"r1b2rk1/pp2qppp/3b1n2/3pn3/8/1PNBPN2/PB3PPP/R2Q1RK1 w - - 0 12","Moves":"c3d5 f6d5 d3h7 g8h7","Rating":2023,"NbPlays":302,"Popularity":88,"Themes":"advantage hangingPiece opening short","OpeningFamily":"","Opening":"","OpeningVariation":"","ECO":"","OpeningTags":"Semi-Slav_Defense Semi-Slav_Defense_Main_Line"},{"PuzzleId":"PYLI2","Fen":"rnb1k1r1/pp3p1R/2pb1q1n/3p3p/3P4/2N1PN1P/PPQ2P2/R1B1KB2 w Qq - 0 13","Moves":"c3d5 f6f3 c2e4 f3e4","Rating":1258,"NbPlays":5392,"Popularity":87,"Themes":"advantage hangingPiece master opening short","OpeningFamily":"","Opening":"","OpeningVariation":"","ECO":"","OpeningTags":"Semi-Slav_Defense Semi-Slav_Defense_Main_Line"},{"PuzzleId":"kG7sr","Fen":"rn1q1rk1/1b2bppN/p3pn1p/1pp5/3P4/2NQP3/PPB2PPP/R1B2RK1 b - - 1 13","Moves":"c5c4 h7f6 e7f6 d3h7","Rating":878,"NbPlays":1595,"Popularity":96,"Themes":"clearance kingsideAttack mate mateIn2 opening short","OpeningFamily":"","Opening":"","OpeningVariation":"","ECO":"","OpeningTags":"Semi-Slav_Defense Semi-Slav_Defense_Main_Line"},{"PuzzleId":"rgMYf","Fen":"r1bqk2r/p2nbppp/1pp1pn2/3p4/2PP4/1PNBPN2/P4PPP/R1BQK2R w KQkq - 1 8","Moves":"e3e4 e7b4 c1d2 b4c3 d2c3 d5e4 d3c2 e4f3","Rating":2100,"NbPlays":687,"Popularity":90,"Themes":"advantage fork opening pin veryLong","OpeningFamily":"","Opening":"","OpeningVariation":"","ECO":"","OpeningTags":"Semi-Slav_Defense Semi-Slav_Defense_Main_Line"},{"PuzzleId":"AbrWz","Fen":"rn3rk1/pb2bp1p/4p1p1/1ppqP3/3P4/3B1N2/PPQ2PPP/R1B2RK1 w - - 0 14","Moves":"d3e4 d5e4 c2e4 b7e4","Rating":996,"NbPlays":501,"Popularity":90,"Themes":"crushing opening short","OpeningFamily":"","Opening":"","OpeningVariation":"","ECO":"","OpeningTags":"Semi-Slav_Defense Semi-Slav_Defense_Main_Line"},{"PuzzleId":"MWP0o","Fen":"r1b2rk1/pp3ppp/8/3p4/6nq/2NBP3/PPQ2PP1/R1BR2K1 w - - 3 15","Moves":"d3f5 h4h2 g1f1 h2h1 f1e2 h1g2","Rating":2118,"NbPlays":127,"Popularity":85,"Themes":"crushing deflection kingsideAttack long opening","OpeningFamily":"","Opening":"","OpeningVariation":"","ECO":"","OpeningTags":"Semi-Slav_Defense Semi-Slav_Defense_Main_Line"},{"PuzzleId":"YUUQK","Fen":"r1b1k2r/ppb2ppp/2p2n2/2Ppq3/1P6/P1NBP3/3B1PPP/R2QK2R w KQkq - 0 13","Moves":"e1g1 e5h2","Rating":708,"NbPlays":121,"Popularity":90,"Themes":"kingsideAttack mate mateIn1 oneMove opening","OpeningFamily":"","Opening":"","OpeningVariation":"","ECO":"","OpeningTags":"Semi-Slav_Defense Semi-Slav_Defense_Main_Line"},{"PuzzleId":"iVQBn","Fen":"rn1q1rk1/pb2bpp1/1p2pn1p/2p3N1/3PN2P/3BP3/PPQ2PP1/R1B1K2R b KQ - 3 12","Moves":"f6e4 d3e4 b7e4 c2e4","Rating":1839,"NbPlays":194,"Popularity":87,"Themes":"advantage opening short","OpeningFamily":"","Opening":"","OpeningVariation":"","ECO":"","OpeningTags":"Semi-Slav_Defense Semi-Slav_Defense_Main_Line"},{"PuzzleId":"GBzJl","Fen":"r1b1r1k1/pp1n2pp/2qN1n2/8/8/1QP5/P4PPP/R1B2RK1 b - - 8 17","Moves":"g8h8 d6f7 h8g8 f7h6 g8h8 b3g8 f6g8 h6f7","Rating":1638,"NbPlays":3041,"Popularity":88,"Themes":"doubleCheck kingsideAttack mate mateIn4 opening sacrifice smotheredMate veryLong","OpeningFamily":"","Opening":"","OpeningVariation":"","ECO":"","OpeningTags":"Semi-Slav_Defense Semi-Slav_Defense_Main_Line"},{"PuzzleId":"UUvcf","Fen":"1qrr2k1/pb2bpp1/1p2pn1p/4N3/2PB4/1P6/P3QPPP/1BRR2K1 w - - 0 19","Moves":"e2c2 d8d4 d1d4 b8e5","Rating":1608,"NbPlays":189,"Popularity":89,"Themes":"capturingDefender crushing master masterVsMaster opening short","OpeningFamily":"","Opening":"","OpeningVariation":"","ECO":"","OpeningTags":"Semi-Slav_Defense Semi-Slav_Defense_Main_Line"},{"PuzzleId":"C6mTp","Fen":"r2q1r1k/pb2bpp1/1p2p3/2nnP3/3N4/P1NB4/1PQ2PPP/R1B1R1K1 w - - 0 17","Moves":"c3d5 d8d5 d3f1 d5d4","Rating":1690,"NbPlays":35,"Popularity":85,"Themes":"advantage opening short","OpeningFamily":"","Opening":"","OpeningVariation":"","ECO":"","OpeningTags":"Semi-Slav_Defense Semi-Slav_Defense_Main_Line"},{"PuzzleId":"Uz6NQ","Fen":"rn3rk1/5ppp/2pb4/pp1q3b/3P4/P2B1N1P/1P3PP1/R1BQR1K1 w - - 2 16","Moves":"d3h7 g8h7 f3g5 d5g5 c1g5 h5d1","Rating":2091,"NbPlays":3363,"Popularity":91,"Themes":"crushing hangingPiece long opening","OpeningFamily":"","Opening":"","OpeningVariation":"","ECO":"","OpeningTags":"Semi-Slav_Defense Semi-Slav_Defense_Main_Line"},{"PuzzleId":"g0DTu","Fen":"rnbq1rk1/4bppp/p3pn2/1p6/3PN2P/3BBN2/PP3PP1/R2QK2R b KQ - 0 12","Moves":"c8b7 e4f6 e7f6 d3h7 g8h7 f3g5 h7g8 d1h5 b7e4 g5e4","Rating":2061,"NbPlays":304,"Popularity":86,"Themes":"advantage attraction clearance discoveredAttack kingsideAttack opening sacrifice veryLong","OpeningFamily":"","Opening":"","OpeningVariation":"","ECO":"","OpeningTags":"Semi-Slav_Defense Semi-Slav_Defense_Main_Line"},{"PuzzleId":"wwoz3","Fen":"r1bq1rk1/pp2bppp/2n1pn2/2p5/2PP4/2NBPN2/P1Q2PPP/R1B1K2R w KQ - 2 10","Moves":"d4c5 c6b4 d3h7 f6h7","Rating":1504,"NbPlays":6314,"Popularity":91,"Themes":"crushing opening short","OpeningFamily":"","Opening":"","OpeningVariation":"","ECO":"","OpeningTags":"Semi-Slav_Defense Semi-Slav_Defense_Main_Line"},{"PuzzleId":"KDelO","Fen":"r1b2rk1/ppqn1pp1/4p2p/3p4/2Ppn3/P2QPP2/1PBB2PP/1R2NRK1 b - - 0 16","Moves":"e4d2 d3h7","Rating":550,"NbPlays":783,"Popularity":96,"Themes":"mate mateIn1 oneMove opening","OpeningFamily":"","Opening":"","OpeningVariation":"","ECO":"","OpeningTags":"Semi-Slav_Defense Semi-Slav_Defense_Main_Line"},{"PuzzleId":"k0FDw","Fen":"r2qk2r/pb1nbppp/4p3/1p1pP3/3P4/3B1N2/PPQ2PPP/R1B1K2R w KQkq - 0 13","Moves":"d3b5 d8a5 e1f1 a5b5","Rating":1198,"NbPlays":951,"Popularity":100,"Themes":"advantage fork opening short","OpeningFamily":"","Opening":"","OpeningVariation":"","ECO":"","OpeningTags":"Semi-Slav_Defense Semi-Slav_Defense_Main_Line"},{"PuzzleId":"i4IiK","Fen":"r2q1rk1/pb2bpp1/1pp1p2p/3nP3/8/P1NBP2P/1PQ2PP1/R1BR2K1 b - - 0 14","Moves":"d5c3 d3h7 g8h8 d1d8","Rating":1177,"NbPlays":10505,"Popularity":97,"Themes":"crushing discoveredAttack opening short","OpeningFamily":"","Opening":"","OpeningVariation":"","ECO":"","OpeningTags":"Semi-Slav_Defense Semi-Slav_Defense_Main_Line"},{"PuzzleId":"sgBUq","Fen":"rn3rk1/pp4pp/2p5/3p3q/3Pp3/2N1PPQb/PP1N4/R1B3RK b - - 7 17","Moves":"e4f3 g3g7","Rating":536,"NbPlays":108,"Popularity":100,"Themes":"kingsideAttack mate mateIn1 oneMove opening","OpeningFamily":"","Opening":"","OpeningVariation":"","ECO":"","OpeningTags":"Semi-Slav_Defense Semi-Slav_Defense_Main_Line"},{"PuzzleId":"ArrbE","Fen":"r1bq1rk1/1p2bppp/2p1pn2/4P3/2nP4/2N2N2/PBB2PPP/1R1QR1K1 b - - 2 15","Moves":"f6d5 d1d3 g7g6 d3c4","Rating":2026,"NbPlays":6742,"Popularity":95,"Themes":"crushing opening short","OpeningFamily":"","Opening":"","OpeningVariation":"","ECO":"","OpeningTags":"Semi-Slav_Defense Semi-Slav_Defense_Main_Line"},{"PuzzleId":"n7FS2","Fen":"2rqkb1r/pp3ppp/1n2pn2/3p4/b2P4/P1NBPN2/1P1B1PPP/RQ2K2R b KQk - 5 11","Moves":"f8e7 c3a4 b6a4 d3b5 e8f8 b5a4","Rating":1529,"NbPlays":41,"Popularity":84,"Themes":"advantage fork long opening","OpeningFamily":"","Opening":"","OpeningVariation":"","ECO":"","OpeningTags":"Semi-Slav_Defense Semi-Slav_Defense_Main_Line"},{"PuzzleId":"71Kh1","Fen":"r1b1k2r/pp1n2pp/3b4/3P1p1q/4p3/4BN2/PPB2PPP/R2Q1RK1 w kq - 0 15","Moves":"f3d4 h5h2","Rating":1327,"NbPlays":13,"Popularity":67,"Themes":"kingsideAttack master mate mateIn1 oneMove opening","OpeningFamily":"","Opening":"","OpeningVariation":"","ECO":"","OpeningTags":"Semi-Slav_Defense Semi-Slav_Defense_Main_Line"},{"PuzzleId":"5DU5o","Fen":"r2q1rk1/ppbn1ppp/2p5/2P5/1P2N3/3Q1P1b/P4P1P/RBB1R1K1 b - - 2 16","Moves":"d7e5 e4f6 g7f6 d3h7","Rating":1622,"NbPlays":187,"Popularity":89,"Themes":"discoveredAttack kingsideAttack mate mateIn2 opening sacrifice short","OpeningFamily":"","Opening":"","OpeningVariation":"","ECO":"","OpeningTags":"Semi-Slav_Defense Semi-Slav_Defense_Main_Line"},{"PuzzleId":"BfnBx","Fen":"rnb1kb1r/ppq2ppp/4p3/3p4/3P4/2P1PN2/P1QB1PPP/2R1KB1R b Kkq - 3 10","Moves":"f8a3 c2a4 b8c6 a4a3","Rating":983,"NbPlays":2028,"Popularity":95,"Themes":"crushing fork opening short","OpeningFamily":"","Opening":"","OpeningVariation":"","ECO":"","OpeningTags":"Semi-Slav_Defense Semi-Slav_Defense_Main_Line"},{"PuzzleId":"AfizW","Fen":"rn3rk1/ppb2pp1/2pq1n1p/3p4/1P1P4/P1N1Pb1P/2Q1BPP1/R1B2RK1 w - - 0 14","Moves":"e2f3 d6h2","Rating":403,"NbPlays":112,"Popularity":86,"Themes":"mate mateIn1 oneMove opening","OpeningFamily":"","Opening":"","OpeningVariation":"","ECO":"","OpeningTags":"Semi-Slav_Defense Semi-Slav_Defense_Main_Line"},{"PuzzleId":"L0TPj","Fen":"rnb1k2r/1p3ppp/1qp1p3/p2n4/1b1P4/1QN1PN2/PP1B1PPP/R3KB1R w KQkq - 0 9","Moves":"a2a4 b4c3 b3b6 c3d2 f3d2 d5b6","Rating":1694,"NbPlays":2045,"Popularity":93,"Themes":"advantage long opening sacrifice","OpeningFamily":"","Opening":"","OpeningVariation":"","ECO":"","OpeningTags":"Semi-Slav_Defense Semi-Slav_Defense_Main_Line"},{"PuzzleId":"iFonW","Fen":"rn1q1rk1/ppb3pp/2p5/4Pp2/3PB1b1/1P3N2/P4PPP/R1BQ1RK1 w - f6 0 14","Moves":"h2h3 f5e4 h3g4 e4f3","Rating":1672,"NbPlays":12334,"Popularity":94,"Themes":"advantage hangingPiece opening short","OpeningFamily":"","Opening":"","OpeningVariation":"","ECO":"","OpeningTags":"Semi-Slav_Defense Semi-Slav_Defense_Main_Line"},{"PuzzleId":"O2XSY","Fen":"rn1q1rk1/1p1bbppp/2p5/p2n4/3PN3/3Q1N1P/PPB2PP1/R1B1K2R b KQ - 4 13","Moves":"d5b4 e4f6 g7f6 d3h7","Rating":1129,"NbPlays":91,"Popularity":75,"Themes":"discoveredAttack kingsideAttack mate mateIn2 opening sacrifice short","OpeningFamily":"","Opening":"","OpeningVariation":"","ECO":"","OpeningTags":"Semi-Slav_Defense Semi-Slav_Defense_Main_Line"},{"PuzzleId":"PoW6D","Fen":"r1bq1rk1/pp3ppp/5n2/3pb3/8/P1NBP3/1PQ2PPP/R1B2RK1 b - - 1 12","Moves":"e5h2 g1h2 f6g4 h2g3","Rating":1928,"NbPlays":491,"Popularity":88,"Themes":"advantage hangingPiece opening short","OpeningFamily":"","Opening":"","OpeningVariation":"","ECO":"","OpeningTags":"Semi-Slav_Defense Semi-Slav_Defense_Main_Line"},{"PuzzleId":"aMeIn","Fen":"r1bqr1k1/3n1ppp/4p3/p2p4/3Pn3/P3PN2/4BPPP/R2QBRK1 w - - 2 17","Moves":"f3d2 e4c3 d1b3 c3e2","Rating":1561,"NbPlays":1748,"Popularity":89,"Themes":"crushing opening short","OpeningFamily":"","Opening":"","OpeningVariation":"","ECO":"","OpeningTags":"Semi-Slav_Defense Semi-Slav_Defense_Main_Line"},{"PuzzleId":"aNkNN","Fen":"r1b1k2r/pp2qpp1/2p2n1p/2Ppb3/1P6/2NBP3/PB3PPP/R2QR1K1 b kq - 3 13","Moves":"e5h2 g1h2 f6g4 h2g1","Rating":1354,"NbPlays":1308,"Popularity":88,"Themes":"advantage defensiveMove hangingPiece opening short","OpeningFamily":"","Opening":"","OpeningVariation":"","ECO":"","OpeningTags":"Semi-Slav_Defense Semi-Slav_Defense_Main_Line"},{"PuzzleId":"Cjr0j","Fen":"r1b1r1k1/ppq2ppp/2p2n2/2bp4/3N1P2/3BP2P/PPQ3P1/R1B2RK1 b - - 3 15","Moves":"f6e4 d3e4 e8e4 c2c5","Rating":1245,"NbPlays":1659,"Popularity":92,"Themes":"advantage capturingDefender opening short","OpeningFamily":"","Opening":"","OpeningVariation":"","ECO":"","OpeningTags":"Semi-Slav_Defense Semi-Slav_Defense_Main_Line"},{"PuzzleId":"GamL6","Fen":"rnbqkb1r/pp3ppp/2p5/4N3/3Pp3/4P3/PP3PPP/R1BQKB1R b KQkq - 1 8","Moves":"f7f6 d1h5 g7g6 e5g6 h7g6 h5h8","Rating":1111,"NbPlays":352,"Popularity":91,"Themes":"advantage long opening","OpeningFamily":"","Opening":"","OpeningVariation":"","ECO":"","OpeningTags":"Semi-Slav_Defense Semi-Slav_Defense_Main_Line"},{"PuzzleId":"ieERL","Fen":"2rq1rk1/1b2bppp/p3p3/1pNnP3/8/P2B1N2/1P2QPPP/R1B2RK1 b - - 0 16","Moves":"e7c5 d3h7 g8h7 f3g5 h7g8 e2h5","Rating":1789,"NbPlays":118,"Popularity":87,"Themes":"advantage attraction clearance kingsideAttack long master opening sacrifice","OpeningFamily":"","Opening":"","OpeningVariation":"","ECO":"","OpeningTags":"Semi-Slav_Defense Semi-Slav_Defense_Main_Line"},{"PuzzleId":"0uiAt","Fen":"r1bqk2r/3n1ppp/3bpn2/1B2P3/3p4/5N2/PP3PPP/R1BQK2R w KQkq - 1 13","Moves":"e5d6 d8a5 c1d2 a5b5","Rating":1037,"NbPlays":228,"Popularity":94,"Themes":"advantage fork opening short","OpeningFamily":"","Opening":"","OpeningVariation":"","ECO":"","OpeningTags":"Semi-Slav_Defense Semi-Slav_Defense_Main_Line"},{"PuzzleId":"8zUiE","Fen":"r1b2rk1/1pb2pp1/p2qp2p/8/1P1nB3/P4N2/2Q2PPP/R1B2RK1 w - - 0 17","Moves":"f3d4 d6h2","Rating":1087,"NbPlays":274,"Popularity":87,"Themes":"kingsideAttack mate mateIn1 oneMove opening","OpeningFamily":"","Opening":"","OpeningVariation":"","ECO":"","OpeningTags":"Semi-Slav_Defense Semi-Slav_Defense_Main_Line"},{"PuzzleId":"9zOT5","Fen":"r1bq1rk1/ppbn1pp1/2p1pn1p/3p2N1/2PP3P/2N1P3/PPQB1PP1/2KR1B1R b - - 0 10","Moves":"f6g4 c2h7","Rating":645,"NbPlays":157,"Popularity":95,"Themes":"mate mateIn1 oneMove opening","OpeningFamily":"","Opening":"","OpeningVariation":"","ECO":"","OpeningTags":"Semi-Slav_Defense Semi-Slav_Defense_Main_Line"},{"PuzzleId":"ywYod","Fen":"r1b1k2r/pp3ppp/4p3/q2p4/1nPNn3/P3P3/1B3PPP/R2QKB1R w KQkq - 0 13","Moves":"a3b4 a5b4 e1e2 b4b2","Rating":1153,"NbPlays":206,"Popularity":73,"Themes":"crushing fork opening short","OpeningFamily":"","Opening":"","OpeningVariation":"","ECO":"","OpeningTags":"Semi-Slav_Defense Semi-Slav_Defense_Main_Line"},{"PuzzleId":"BxU1W","Fen":"r2qrbk1/pp1n1ppp/2p2n2/3p2N1/3P2b1/3BP3/PPQN1PPP/R1B2RK1 b - - 11 12","Moves":"h7h6 d3h7 f6h7 c2h7","Rating":961,"NbPlays":1812,"Popularity":94,"Themes":"kingsideAttack mate mateIn2 opening short","OpeningFamily":"","Opening":"","OpeningVariation":"","ECO":"","OpeningTags":"Semi-Slav_Defense Semi-Slav_Defense_Main_Line"},{"PuzzleId":"NIqNF","Fen":"r1b1r1k1/ppq2ppp/2p3n1/7n/3NP3/2N1BPbP/PP2R1P1/R2Q1BK1 w - - 5 17","Moves":"e2c2 g3h2 g1h1 h5g3 h1h2 g3f1 h2g1 f1e3","Rating":1486,"NbPlays":906,"Popularity":92,"Themes":"crushing doubleCheck kingsideAttack opening veryLong","OpeningFamily":"","Opening":"","OpeningVariation":"","ECO":"","OpeningTags":"Semi-Slav_Defense Semi-Slav_Defense_Main_Line"},{"PuzzleId":"qePmn","Fen":"rn1qkb1r/p4ppp/b3pn2/1p1p4/3P4/1PN1PN2/P3BPPP/R1BQK2R w KQkq - 0 9","Moves":"e2b5 a6b5 c3b5 d8a5","Rating":1168,"NbPlays":760,"Popularity":88,"Themes":"advantage opening short","OpeningFamily":"","Opening":"","OpeningVariation":"","ECO":"","OpeningTags":"Semi-Slav_Defense Semi-Slav_Defense_Main_Line"},{"PuzzleId":"HvB4P","Fen":"r2q1rk1/pb1nbp2/1pp1Nnp1/4N3/2PP4/8/PPQ2PPP/R1B2RK1 b - - 0 14","Moves":"f7e6 c2g6 g8h8 c1h6","Rating":1954,"NbPlays":1319,"Popularity":96,"Themes":"advantage kingsideAttack master opening short","OpeningFamily":"","Opening":"","OpeningVariation":"","ECO":"","OpeningTags":"Semi-Slav_Defense Semi-Slav_Defense_Main_Line"},{"PuzzleId":"MrNmo","Fen":"r1b1k2r/pp3ppp/2p5/2Pp4/6n1/2NBPP2/PP4Pq/R1BQR1K1 w kq - 1 15","Moves":"g1f1 h2h1 f1e2 h1g2","Rating":1207,"NbPlays":180,"Popularity":73,"Themes":"deflection mate mateIn2 opening short","OpeningFamily":"","Opening":"","OpeningVariation":"","ECO":"","OpeningTags":"Semi-Slav_Defense Semi-Slav_Defense_Main_Line"},{"PuzzleId":"JeeFz","Fen":"r2qrn1k/3bb1pp/p1n5/1p2N3/3P4/2NQP1P1/PPB4P/R1B2RK1 b - - 0 18","Moves":"c6e5 f1f8 e7f8 d3h7","Rating":1621,"NbPlays":26464,"Popularity":96,"Themes":"kingsideAttack mate mateIn2 opening short","OpeningFamily":"","Opening":"","OpeningVariation":"","ECO":"","OpeningTags":"Semi-Slav_Defense Semi-Slav_Defense_Main_Line"},{"PuzzleId":"2CbLG","Fen":"rnbq1rk1/pp2bppp/2p2n2/4N3/2PPN3/3B4/PP3PPP/R1BQK2R b KQ - 0 9","Moves":"d8d4 e4f6 e7f6 d3h7 g8h7 d1d4","Rating":1384,"NbPlays":200,"Popularity":83,"Themes":"advantage discoveredAttack kingsideAttack long opening","OpeningFamily":"","Opening":"","OpeningVariation":"","ECO":"","OpeningTags":"Semi-Slav_Defense Semi-Slav_Defense_Main_Line"},{"PuzzleId":"PDgqK","Fen":"2rq1rk1/1b1nbppp/1p3n2/pP6/3p4/P1N2B1P/1B1N1PP1/R2Q1RK1 w - - 0 17","Moves":"f3b7 d4c3 b7c8 c3b2","Rating":1528,"NbPlays":1217,"Popularity":89,"Themes":"advancedPawn advantage fork opening short","OpeningFamily":"","Opening":"","OpeningVariation":"","ECO":"","OpeningTags":"Semi-Slav_Defense Semi-Slav_Defense_Main_Line"},{"PuzzleId":"iHVie","Fen":"r1b1k2r/ppb1qppp/2p2n2/2Ppn3/1P6/2NBPN2/P4PPP/R1BQ1RK1 w kq - 0 11","Moves":"f3e5 e7e5 f2f4 e5c3","Rating":1566,"NbPlays":85,"Popularity":87,"Themes":"advantage opening short","OpeningFamily":"","Opening":"","OpeningVariation":"","ECO":"","OpeningTags":"Semi-Slav_Defense Semi-Slav_Defense_Main_Line"},{"PuzzleId":"mOYAr","Fen":"r1bq1rk1/pp2bppp/4pn2/2pn4/P2P4/2NBPN2/1PQ2PPP/R1B2RK1 w - - 0 12","Moves":"d4c5 d5b4 d3h7 f6h7","Rating":1869,"NbPlays":254,"Popularity":87,"Themes":"advantage opening short","OpeningFamily":"","Opening":"","OpeningVariation":"","ECO":"","OpeningTags":"Semi-Slav_Defense Semi-Slav_Defense_Main_Line"},{"PuzzleId":"nNgAn","Fen":"rn2k2r/p1q1bppp/2b2n2/1BpNN3/8/PQ2P3/1P3PPP/R1B1K2R b KQkq - 0 13","Moves":"f6d5 b5c6 b8c6 b3d5 c6e5 d5a8","Rating":2395,"NbPlays":172,"Popularity":79,"Themes":"advantage fork intermezzo long opening","OpeningFamily":"","Opening":"","OpeningVariation":"","ECO":"","OpeningTags":"Semi-Slav_Defense Semi-Slav_Defense_Main_Line"},{"PuzzleId":"1mWoC","Fen":"r1bq1rk1/pp1nbpp1/2p1pn2/6P1/2PPN3/2B5/PPQ2PP1/R3KB1R b KQ - 0 13","Moves":"f6e4 c2e4 f7f5 e4e6 f8f7 g5g6","Rating":2219,"NbPlays":60,"Popularity":84,"Themes":"crushing kingsideAttack long opening","OpeningFamily":"","Opening":"","OpeningVariation":"","ECO":"","OpeningTags":"Semi-Slav_Defense Semi-Slav_Defense_Main_Line"},{"PuzzleId":"O14th","Fen":"r2q1rk1/2nbbppp/4p3/1ppnP3/p2P4/2NQ1N2/PPB2PPP/2R1BRK1 b - - 1 16","Moves":"d5b4 d3h7","Rating":686,"NbPlays":266,"Popularity":83,"Themes":"kingsideAttack mate mateIn1 oneMove opening","OpeningFamily":"","Opening":"","OpeningVariation":"","ECO":"","OpeningTags":"Semi-Slav_Defense Semi-Slav_Defense_Main_Line"},{"PuzzleId":"uXKXV","Fen":"rnbq1rk1/p4ppp/1pp1pn2/8/2QP4/2PBPN2/P4PPP/R1B1K2R w KQ - 0 10","Moves":"e1g1 c8a6 c4a4 a6d3","Rating":1648,"NbPlays":22632,"Popularity":96,"Themes":"advantage opening short skewer","OpeningFamily":"","Opening":"","OpeningVariation":"","ECO":"","OpeningTags":"Semi-Slav_Defense Semi-Slav_Defense_Main_Line"},{"PuzzleId":"WCS9C","Fen":"r1bq1rk1/3nbppp/p3p3/1p6/3PQ3/1P1B1N2/P4PPP/R1B2RK1 b - - 0 13","Moves":"a8b8 e4h7","Rating":484,"NbPlays":514,"Popularity":100,"Themes":"kingsideAttack mate mateIn1 oneMove opening","OpeningFamily":"","Opening":"","OpeningVariation":"","ECO":"","OpeningTags":"Semi-Slav_Defense Semi-Slav_Defense_Main_Line"},{"PuzzleId":"w47pM","Fen":"r2qr1k1/pb1nbppp/1p2pn2/6N1/3P4/3B1N2/PPQ2PPP/R1B1R1K1 b - - 3 13","Moves":"h7h6 d3h7 g8f8 g5f7 f8f7 c2g6","Rating":2292,"NbPlays":230,"Popularity":85,"Themes":"advantage attraction kingsideAttack long opening sacrifice","OpeningFamily":"","Opening":"","OpeningVariation":"","ECO":"","OpeningTags":"Semi-Slav_Defense Semi-Slav_Defense_Main_Line"},{"PuzzleId":"QoDN2","Fen":"r1bq1rk1/ppb2ppp/2p2n2/2Ppn3/1P6/P1N1PN2/1B2BPPP/R2Q1RK1 b - - 1 12","Moves":"c8g4 f3e5 c7e5 e2g4 f6g4 d1g4","Rating":1170,"NbPlays":72,"Popularity":67,"Themes":"crushing discoveredAttack long opening","OpeningFamily":"","Opening":"","OpeningVariation":"","ECO":"","OpeningTags":"Semi-Slav_Defense Semi-Slav_Defense_Main_Line"},{"PuzzleId":"M4BoU","Fen":"rn1qrk1Q/pp1b2p1/2p1p3/3nP1N1/3P4/2b5/PP3PPP/R1B2RK1 b - - 6 18","Moves":"f8e7 h8g7","Rating":1156,"NbPlays":6,"Popularity":33,"Themes":"mate mateIn1 oneMove opening","OpeningFamily":"","Opening":"","OpeningVariation":"","ECO":"","OpeningTags":"Semi-Slav_Defense Semi-Slav_Defense_Main_Line"},{"PuzzleId":"e3DS3","Fen":"r1b2rk1/2q2ppp/p3p3/1pb1n3/4P1n1/P1N1B3/1PN2PPP/R2QRBK1 w - - 7 17","Moves":"e3c5 e5f3 g2f3 c7h2","Rating":1905,"NbPlays":494,"Popularity":91,"Themes":"discoveredAttack kingsideAttack mate mateIn2 opening sacrifice short","OpeningFamily":"","Opening":"","OpeningVariation":"","ECO":"","OpeningTags":"Semi-Slav_Defense Semi-Slav_Defense_Main_Line"},{"PuzzleId":"Plfls","Fen":"r1bk3r/pp1n2p1/2pN3p/2P2p2/3P2nq/2N1P3/PP3PP1/R1BQRK2 w - - 2 18","Moves":"d6f5 h4f2","Rating":1739,"NbPlays":130,"Popularity":80,"Themes":"mate mateIn1 oneMove opening","OpeningFamily":"","Opening":"","OpeningVariation":"","ECO":"","OpeningTags":"Semi-Slav_Defense Semi-Slav_Defense_Main_Line"},{"PuzzleId":"26GFD","Fen":"r1b2rk1/ppq2ppp/2n1pn2/2Pp4/3P4/P3PN2/5PPP/R1BQKB1R w KQ - 1 11","Moves":"f1b5 c7a5 e1f1 a5b5","Rating":987,"NbPlays":91,"Popularity":91,"Themes":"crushing fork opening short","OpeningFamily":"","Opening":"","OpeningVariation":"","ECO":"","OpeningTags":"Semi-Slav_Defense Semi-Slav_Defense_Main_Line"},{"PuzzleId":"CH8Df","Fen":"r2qr1k1/pp1n1ppp/2pb4/7b/3PB3/5N1P/PP3PP1/R1BQR1K1 w - - 1 14","Moves":"d1c2 h5f3 e4h7 g8h8 e1e8 d8e8","Rating":2031,"NbPlays":177,"Popularity":86,"Themes":"crushing long opening","OpeningFamily":"","Opening":"","OpeningVariation":"","ECO":"","OpeningTags":"Semi-Slav_Defense Semi-Slav_Defense_Main_Line"},{"PuzzleId":"plQ9t","Fen":"r1bq1rk1/pp3pp1/1np1pP2/6NQ/1b1P4/2N5/PP3PPP/R1B2RK1 b - - 0 15","Moves":"d8f6 h5h7","Rating":1223,"NbPlays":14,"Popularity":68,"Themes":"mate mateIn1 oneMove opening","OpeningFamily":"","Opening":"","OpeningVariation":"","ECO":"","OpeningTags":"Semi-Slav_Defense Semi-Slav_Defense_Main_Line"},{"PuzzleId":"QSNXE","Fen":"rn1q1rk1/p3bppp/b3pn2/8/3p4/2NBPN2/PP3PPP/R1BQ1RK1 w - - 0 12","Moves":"f3d4 a6d3 d1d3 e6e5 f1d1 e5d4","Rating":1872,"NbPlays":339,"Popularity":76,"Themes":"advantage long opening","OpeningFamily":"","Opening":"","OpeningVariation":"","ECO":"","OpeningTags":"Semi-Slav_Defense Semi-Slav_Defense_Main_Line"},{"PuzzleId":"3Mqjc","Fen":"r1bqrnk1/pp1n1ppp/2pb4/3pN2Q/3P1P2/P1NBP2P/1P4P1/R1B2RK1 b - - 2 13","Moves":"f7f6 d3h7 f8h7 h5f7 g8h8 e5g6","Rating":2033,"NbPlays":1309,"Popularity":91,"Themes":"kingsideAttack long mate mateIn3 opening sacrifice","OpeningFamily":"","Opening":"","OpeningVariation":"","ECO":"","OpeningTags":"Semi-Slav_Defense Semi-Slav_Defense_Main_Line"},{"PuzzleId":"VePVu","Fen":"r1bqk2r/1p1n1p2/p1pbp1B1/8/3P4/2P1PN2/P1Q2PPP/R1B2RK1 b kq - 0 13","Moves":"f7g6 c2g6 e8f8 e3e4 d6h2 f3h2","Rating":2644,"NbPlays":510,"Popularity":92,"Themes":"advantage long opening quietMove","OpeningFamily":"","Opening":"","OpeningVariation":"","ECO":"","OpeningTags":"Semi-Slav_Defense Semi-Slav_Defense_Main_Line"},{"PuzzleId":"Lm5eM","Fen":"rbb1qrk1/p5p1/1p2pn1p/3p4/3P2N1/P7/1PQ2PPP/RBB2RK1 b - - 3 18","Moves":"e8h5 g4f6 f8f6 c2c8 f6f8 c8e6","Rating":2274,"NbPlays":6569,"Popularity":92,"Themes":"crushing deflection kingsideAttack long opening","OpeningFamily":"","Opening":"","OpeningVariation":"","ECO":"","OpeningTags":"Semi-Slav_Defense Semi-Slav_Defense_Main_Line"},{"PuzzleId":"4WgXs","Fen":"rnbq1rk1/pp3ppp/3bp3/2p5/2PPB2P/5N2/PP3PP1/R1BQK2R b KQ - 0 10","Moves":"b8c6 e4h7 g8h7 f3g5","Rating":1791,"NbPlays":4390,"Popularity":93,"Themes":"attraction crushing kingsideAttack opening sacrifice short","OpeningFamily":"","Opening":"","OpeningVariation":"","ECO":"","OpeningTags":"Semi-Slav_Defense Semi-Slav_Defense_Main_Line"},{"PuzzleId":"XUNFp","Fen":"rnb1r1k1/ppb2ppp/2pq4/8/3PN3/5N1P/PP3PP1/R1BQR1K1 b - - 0 13","Moves":"d6d5 e4f6 g7f6 e1e8","Rating":909,"NbPlays":298,"Popularity":94,"Themes":"crushing discoveredAttack kingsideAttack opening short","OpeningFamily":"","Opening":"","OpeningVariation":"","ECO":"","OpeningTags":"Semi-Slav_Defense Semi-Slav_Defense_Main_Line"},{"PuzzleId":"sAY6l","Fen":"rbb1r1k1/ppqn1pp1/5n1p/3p4/3Pp3/1NN1P2P/PP2BPP1/R1BQ1RK1 w - - 2 15","Moves":"c3b5 c7h2","Rating":643,"NbPlays":237,"Popularity":100,"Themes":"mate mateIn1 oneMove opening","OpeningFamily":"","Opening":"","OpeningVariation":"","ECO":"","OpeningTags":"Semi-Slav_Defense Semi-Slav_Defense_Main_Line"},{"PuzzleId":"4HWUP","Fen":"rnb1r1k1/pp4pp/2pb4/3p1p2/3Pn2q/P1NBP3/1P1N1PPP/R1BQR1K1 w - - 2 12","Moves":"d2f3 d6h2 f3h2 h4f2 g1h1 e4g3","Rating":2175,"NbPlays":307,"Popularity":83,"Themes":"kingsideAttack long mate mateIn3 opening","OpeningFamily":"","Opening":"","OpeningVariation":"","ECO":"","OpeningTags":"Semi-Slav_Defense Semi-Slav_Defense_Main_Line"},{"PuzzleId":"sPjj9","Fen":"1rbq1rk1/pp3ppp/2p2n2/3Pb3/8/1PNBP3/PB3PPP/R2Q1RK1 b - - 0 12","Moves":"f6d5 d3h7 g8h7 d1h5 h7g8 h5e5","Rating":2391,"NbPlays":1111,"Popularity":89,"Themes":"attraction crushing fork long opening sacrifice","OpeningFamily":"","Opening":"","OpeningVariation":"","ECO":"","OpeningTags":"Semi-Slav_Defense Semi-Slav_Defense_Main_Line"},{"PuzzleId":"Q8AAk","Fen":"r1b2rk1/ppq3pn/2pb3p/4Np2/2QP4/P7/1PB2PPP/R1B1R1K1 b - - 1 17","Moves":"g8h8 e5g6","Rating":1132,"NbPlays":1528,"Popularity":95,"Themes":"mate mateIn1 oneMove opening","OpeningFamily":"","Opening":"","OpeningVariation":"","ECO":"","OpeningTags":"Semi-Slav_Defense Semi-Slav_Defense_Main_Line"},{"PuzzleId":"llY3L","Fen":"r1bqr1k1/pp3ppp/2pb4/8/2BNnP2/2N4P/PB4P1/R2Q1RK1 w - - 0 17","Moves":"d4f3 d8b6 f3d4 b6b2 c4f7 g8f7 c3e4 e8e4","Rating":2172,"NbPlays":73,"Popularity":87,"Themes":"advantage fork opening veryLong","OpeningFamily":"","Opening":"","OpeningVariation":"","ECO":"","OpeningTags":"Semi-Slav_Defense Semi-Slav_Defense_Main_Line"},{"PuzzleId":"CylLa","Fen":"r1bq1rk1/3nbppp/p3pn2/1ppP4/4PB2/2NB1N2/PP3PPP/R2Q1RK1 b - - 2 12","Moves":"d7b6 d5d6 e7d6 f4d6 d8d6 e4e5","Rating":2416,"NbPlays":179,"Popularity":84,"Themes":"advantage long opening","OpeningFamily":"","Opening":"","OpeningVariation":"","ECO":"","OpeningTags":"Semi-Slav_Defense Semi-Slav_Defense_Main_Line"},{"PuzzleId":"Y5wDr","Fen":"r2q1rk1/pp1b1ppp/4p3/2bn4/8/PB2PN1P/1P2KPP1/R1BQR3 w - - 0 15","Moves":"b3d5 d7b5 d1d3 b5d3","Rating":901,"NbPlays":100,"Popularity":78,"Themes":"crushing opening short","OpeningFamily":"","Opening":"","OpeningVariation":"","ECO":"","OpeningTags":"Semi-Slav_Defense Semi-Slav_Defense_Main_Line"},{"PuzzleId":"exkLb","Fen":"r1b2rk1/pp1nbppp/1q2pn2/8/2PN4/2NB4/PP3PPP/R1BQR1K1 b - - 2 12","Moves":"b6d4 d3h7 f6h7 d1d4","Rating":1075,"NbPlays":6263,"Popularity":96,"Themes":"crushing discoveredAttack kingsideAttack opening short","OpeningFamily":"","Opening":"","OpeningVariation":"","ECO":"","OpeningTags":"Semi-Slav_Defense Semi-Slav_Defense_Main_Line"},{"PuzzleId":"c8vDH","Fen":"rnb2rk1/pp3p1p/2p1p1p1/2Ppn1q1/8/2NBP3/PP2QPPP/R1B2RK1 b - - 3 13","Moves":"f7f5 f2f4 g5e7 f4e5","Rating":1725,"NbPlays":9463,"Popularity":95,"Themes":"advantage fork opening short","OpeningFamily":"","Opening":"","OpeningVariation":"","ECO":"","OpeningTags":"Semi-Slav_Defense Semi-Slav_Defense_Main_Line"},{"PuzzleId":"jOteb","Fen":"rnbqkb1r/pp3ppp/2p2n2/3pp3/2PP4/2N1PN2/PP3PPP/R1BQKB1R w KQkq - 0 6","Moves":"f1d3 e5e4 d3c2 e4f3","Rating":1336,"NbPlays":3754,"Popularity":92,"Themes":"advantage fork master opening short","OpeningFamily":"","Opening":"","OpeningVariation":"","ECO":"","OpeningTags":"Semi-Slav_Defense Semi-Slav_Defense_Main_Line"},{"PuzzleId":"s8ph6","Fen":"r2q1rk1/1b2bppp/p7/1p1n4/2p5/4BN1P/PPQ2PP1/1BR2RK1 b - - 1 18","Moves":"d5e3 c2h7","Rating":936,"NbPlays":138,"Popularity":62,"Themes":"kingsideAttack mate mateIn1 oneMove opening","OpeningFamily":"","Opening":"","OpeningVariation":"","ECO":"","OpeningTags":"Semi-Slav_Defense Semi-Slav_Defense_Main_Line"},{"PuzzleId":"yDC1y","Fen":"r1bqkb1r/pp3ppp/2n1p3/1B1p4/3P4/4PN2/PP3PPP/R1BQK2R w KQkq - 2 9","Moves":"f3e5 d8a5 c1d2 a5b5","Rating":1366,"NbPlays":63,"Popularity":81,"Themes":"advantage fork opening short","OpeningFamily":"","Opening":"","OpeningVariation":"","ECO":"","OpeningTags":"Semi-Slav_Defense Semi-Slav_Defense_Main_Line"},{"PuzzleId":"c2mjh","Fen":"r1bq1rk1/pp1nbppp/4p3/4P3/4Q3/2NB4/PP3PPP/R1B2RK1 b - - 2 13","Moves":"d7c5 e4h7","Rating":399,"NbPlays":712,"Popularity":91,"Themes":"kingsideAttack mate mateIn1 oneMove opening","OpeningFamily":"","Opening":"","OpeningVariation":"","ECO":"","OpeningTags":"Semi-Slav_Defense Semi-Slav_Defense_Main_Line"},{"PuzzleId":"nJSUY","Fen":"r1b2rk1/ppq2pp1/3bpn1p/8/2Pp2N1/3Q4/PPB2PPP/R1B1R1K1 b - - 1 15","Moves":"f6g4 d3h7","Rating":514,"NbPlays":519,"Popularity":87,"Themes":"mate mateIn1 oneMove opening","OpeningFamily":"","Opening":"","OpeningVariation":"","ECO":"","OpeningTags":"Semi-Slav_Defense Semi-Slav_Defense_Main_Line"},{"PuzzleId":"y0lqP","Fen":"r1bq1rk1/p2n1ppp/3bp3/2p5/3P4/2PQPN2/P1B2PPP/R1B2RK1 b - - 1 12","Moves":"c5d4 d3h7","Rating":550,"NbPlays":225,"Popularity":83,"Themes":"kingsideAttack mate mateIn1 oneMove opening","OpeningFamily":"","Opening":"","OpeningVariation":"","ECO":"","OpeningTags":"Semi-Slav_Defense Semi-Slav_Defense_Main_Line"},{"PuzzleId":"YUUKZ","Fen":"r1bqrbk1/pp1n1ppp/2p1pn2/2Pp2N1/3P4/2NBP3/PPQ2PPP/R1B2RK1 b - - 4 10","Moves":"h7h6 d3h7 f6h7 c2h7","Rating":1044,"NbPlays":1145,"Popularity":85,"Themes":"kingsideAttack mate mateIn2 opening short","OpeningFamily":"","Opening":"","OpeningVariation":"","ECO":"","OpeningTags":"Semi-Slav_Defense Semi-Slav_Defense_Main_Line"},{"PuzzleId":"h9NvS","Fen":"rn1q1rk1/pb3pbp/1p2p1p1/3pP3/3Pn3/2NB1N2/PP1B1PPP/R2Q1RK1 w - - 1 12","Moves":"c3e4 d5e4 d3e4 b7e4","Rating":955,"NbPlays":1372,"Popularity":91,"Themes":"advantage fork opening short","OpeningFamily":"","Opening":"","OpeningVariation":"","ECO":"","OpeningTags":"Semi-Slav_Defense Semi-Slav_Defense_Main_Line"},{"PuzzleId":"hzZmi","Fen":"rnbqr1k1/p4ppp/2pbpP2/8/3P4/3B1N2/Pp3PPP/R1BQ1RK1 w - - 0 13","Moves":"d3h7 g8h7 f3g5 h7g8","Rating":1487,"NbPlays":195,"Popularity":81,"Themes":"advantage defensiveMove hangingPiece master masterVsMaster opening short","OpeningFamily":"","Opening":"","OpeningVariation":"","ECO":"","OpeningTags":"Semi-Slav_Defense Semi-Slav_Defense_Main_Line"},{"PuzzleId":"faegr","Fen":"rnbqk2r/pp3ppp/2p1p3/4N3/1bPPp3/2N1P3/PP3PPP/R1BQK2R b KQkq - 1 8","Moves":"f7f6 d1h5 g7g6 e5g6","Rating":1065,"NbPlays":753,"Popularity":93,"Themes":"advantage opening short","OpeningFamily":"","Opening":"","OpeningVariation":"","ECO":"","OpeningTags":"Semi-Slav_Defense Semi-Slav_Defense_Main_Line"},{"PuzzleId":"aq7Qp","Fen":"r1bqr1k1/pp3ppp/5n2/3Pb3/8/2NB4/PP3PPP/R1BQR1K1 b - - 0 13","Moves":"e5h2 g1h2 e8e1 d1e1","Rating":963,"NbPlays":6,"Popularity":5,"Themes":"advantage hangingPiece opening short","OpeningFamily":"","Opening":"","OpeningVariation":"","ECO":"","OpeningTags":"Semi-Slav_Defense Semi-Slav_Defense_Main_Line"},{"PuzzleId":"YsHme","Fen":"rn1qkb1r/pp1b1ppp/4p3/1B1p4/3P4/4PN2/PP3PPP/R1BQK2R w KQkq - 2 9","Moves":"d1e2 d8a5 c1d2 a5b5","Rating":1265,"NbPlays":653,"Popularity":84,"Themes":"crushing opening short","OpeningFamily":"","Opening":"","OpeningVariation":"","ECO":"","OpeningTags":"Semi-Slav_Defense Semi-Slav_Defense_Main_Line"},{"PuzzleId":"eapS5","Fen":"r2q1rk1/1b1n1ppp/p1p1pn2/1p6/1b1P2N1/2NBP2Q/PP3PPP/R1B2RK1 b - - 5 12","Moves":"f6g4 h3h7","Rating":763,"NbPlays":308,"Popularity":87,"Themes":"kingsideAttack mate mateIn1 oneMove opening","OpeningFamily":"","Opening":"","OpeningVariation":"","ECO":"","OpeningTags":"Semi-Slav_Defense Semi-Slav_Defense_Main_Line"},{"PuzzleId":"fis8O","Fen":"r1bqr1k1/pp1n1p1p/2pbp1p1/6P1/2PPQ3/3BPN2/PP3P1P/R1B1K2R w KQ - 0 12","Moves":"h2h4 f7f5 g5f6 d7f6","Rating":1926,"NbPlays":477,"Popularity":87,"Themes":"crushing master opening short","OpeningFamily":"","Opening":"","OpeningVariation":"","ECO":"","OpeningTags":"Semi-Slav_Defense Semi-Slav_Defense_Main_Line"},{"PuzzleId":"H6IUi","Fen":"2rqr2k/pp3pp1/1bn5/8/1P1p2b1/P3PN2/4BPPP/R1BQ1RK1 w - - 0 18","Moves":"f3d4 b6d4 e2g4 d4a1","Rating":1999,"NbPlays":139,"Popularity":89,"Themes":"advantage opening short","OpeningFamily":"","Opening":"","OpeningVariation":"","ECO":"","OpeningTags":"Semi-Slav_Defense Semi-Slav_Defense_Main_Line"}]