[{"PuzzleId":"6jl18","Fen":"rBbqk1nr/pp3ppp/8/3p4/1bpP4/2N2N2/PP2PPPP/R2QKB1R b KQkq - 0 7","Moves":"a8b8 d1a4 b7b5 a4b4","Rating":1145,"NbPlays":76,"Popularity":80,"Themes":"advantage fork opening short","OpeningFamily":"","Opening":"","OpeningVariation":"","ECO":"","OpeningTags":"Tarrasch_Defense Tarrasch_Defense_Two_Knights_Variation"},{"PuzzleId":"sQGHi","Fen":"r1b1k2r/pp3ppp/2n5/q7/1b1NP3/2N5/PP3PPP/R2QKB1R w KQkq - 3 12","Moves":"d4c6 b4c3 b2c3 a5c3","Rating":983,"NbPlays":139,"Popularity":88,"Themes":"advantage opening short","OpeningFamily":"","Opening":"","OpeningVariation":"","ECO":"","OpeningTags":"Tarrasch_Defense Tarrasch_Defense_Two_Knights_Variation"},{"PuzzleId":"rnq2J","Fen":"r1b1k1nr/pp3ppp/2n5/q7/8/5N2/PP1B1PPP/2RQKB1R b Kkq - 2 13","Moves":"a5a2 f1c4 a2c4 c1c4","Rating":1908,"NbPlays":1376,"Popularity":88,"Themes":"crushing master opening short","OpeningFamily":"","Opening":"","OpeningVariation":"","ECO":"","OpeningTags":"Tarrasch_Defense Tarrasch_Defense_Two_Knights_Variation"},{"PuzzleId":"OkF7Y","Fen":"r1bqk1nr/pp3ppp/8/2bN4/1n6/5N2/PP2PPPP/R1BQKB1R w KQkq - 1 8","Moves":"d1a4 c8d7 a4b4 c5b4","Rating":1160,"NbPlays":2926,"Popularity":95,"Themes":"advantage defensiveMove opening short","OpeningFamily":"","Opening":"","OpeningVariation":"","ECO":"","OpeningTags":"Tarrasch_Defense Tarrasch_Defense_Two_Knights_Variation"},{"PuzzleId":"rS3wC","Fen":"r1bqr1k1/1p2bppp/p1n5/3p4/3Pn3/PQN2N2/1P2BPPP/R1B1R1K1 w - - 0 13","Moves":"b3d5 e4c3 d5d8 c3e2","Rating":1479,"NbPlays":3299,"Popularity":91,"Themes":"crushing opening sacrifice short","OpeningFamily":"","Opening":"","OpeningVariation":"","ECO":"","OpeningTags":"Tarrasch_Defense Tarrasch_Defense_Two_Knights_Variation"},{"PuzzleId":"WNMWW","Fen":"rn2k2r/pN2bppp/5n2/3q2B1/3P2b1/5N2/PP3PPP/R2QKB1R w KQkq - 1 11","Moves":"g5f6 e7b4 f3d2 g4d1","Rating":2022,"NbPlays":1121,"Popularity":94,"Themes":"advantage opening short","OpeningFamily":"","Opening":"","OpeningVariation":"","ECO":"","OpeningTags":"Tarrasch_Defense Tarrasch_Defense_Two_Knights_Variation"},{"PuzzleId":"FMFN2","Fen":"r1b2rk1/1p2bppp/p2q1n2/3p2B1/3n4/2NBP3/PP3PPP/2RQ1RK1 w - - 0 13","Moves":"e3d4 f6g4 f2f4 e7g5","Rating":1601,"NbPlays":2433,"Popularity":92,"Themes":"crushing discoveredAttack opening short","OpeningFamily":"","Opening":"","OpeningVariation":"","ECO":"","OpeningTags":"Tarrasch_Defense Tarrasch_Defense_Two_Knights_Variation"},{"PuzzleId":"bHVR8","Fen":"r1b2rk1/pp3pp1/2n4p/2qNP3/4n3/5N2/PP3PPP/R2QKB1R w KQ - 0 13","Moves":"a1c1 c5f2","Rating":1423,"NbPlays":5616,"Popularity":89,"Themes":"attackingF2F7 mate mateIn1 oneMove opening","OpeningFamily":"","Opening":"","OpeningVariation":"","ECO":"","OpeningTags":"Tarrasch_Defense Tarrasch_Defense_Two_Knights_Variation"},{"PuzzleId":"YZ82m","Fen":"2rq1rk1/1p3ppp/p1n2n2/2bp1b2/5B2/2N1PN1P/PP2BPP1/2RQ1RK1 w - - 0 13","Moves":"c3d5 d8d5 d1d5 f6d5 c1c5 d5f4 e3f4 c6d4 f3d4 c8c5 b2b4 c5d5 d4f5 d5f5","Rating":2401,"NbPlays":1692,"Popularity":90,"Themes":"advantage opening veryLong","OpeningFamily":"","Opening":"","OpeningVariation":"","ECO":"","OpeningTags":"Tarrasch_Defense Tarrasch_Defense_Two_Knights_Variation"},{"PuzzleId":"Qh3lx","Fen":"2rqkbnr/pp3ppp/2n5/1N1p1b2/2pP1B2/P4N2/1P2PPPP/R2QKB1R w KQk - 4 9","Moves":"b5c7 c8c7 f4c7 d8c7","Rating":1034,"NbPlays":1682,"Popularity":95,"Themes":"advantage opening short","OpeningFamily":"","Opening":"","OpeningVariation":"","ECO":"","OpeningTags":"Tarrasch_Defense Tarrasch_Defense_Two_Knights_Variation"},{"PuzzleId":"p8Cvu","Fen":"rn2kbnr/1p3ppp/p3b3/2qp2B1/4P3/P1N2N2/1P3PPP/R2QKB1R b KQkq - 0 9","Moves":"d5e4 d1d8","Rating":1164,"NbPlays":111,"Popularity":60,"Themes":"mate mateIn1 oneMove opening","OpeningFamily":"","Opening":"","OpeningVariation":"","ECO":"","OpeningTags":"Tarrasch_Defense Tarrasch_Defense_Two_Knights_Variation"},{"PuzzleId":"uV4TY","Fen":"rnb2k1r/pp3ppp/1q6/2b1Q3/8/2N2N2/PP2PPPP/R3KB1R w KQ - 3 11","Moves":"e2e3 b8d7 e5g5 f7f6 g5d5 b6b2","Rating":2486,"NbPlays":1847,"Popularity":90,"Themes":"advantage long opening","OpeningFamily":"","Opening":"","OpeningVariation":"","ECO":"","OpeningTags":"Tarrasch_Defense Tarrasch_Defense_Two_Knights_Variation"},{"PuzzleId":"iWNg7","Fen":"r1b2rk1/pp3ppp/2n2n2/q1bp4/8/P1NBPN2/1P1B1PPP/R2QK2R b KQ - 4 10","Moves":"a5b6 c3a4 b6c7 a4c5","Rating":1481,"NbPlays":2555,"Popularity":92,"Themes":"crushing opening short","OpeningFamily":"","Opening":"","OpeningVariation":"","ECO":"","OpeningTags":"Tarrasch_Defense Tarrasch_Defense_Two_Knights_Variation"},{"PuzzleId":"clqBN","Fen":"rn1qkbnr/pp3ppp/8/1bp1N3/3Pp3/1QN5/PP3PPP/R1B1K2R b KQkq - 1 9","Moves":"f7f6 b3f7","Rating":1157,"NbPlays":466,"Popularity":82,"Themes":"mate mateIn1 oneMove opening","OpeningFamily":"","Opening":"","OpeningVariation":"","ECO":"","OpeningTags":"Tarrasch_Defense Tarrasch_Defense_Two_Knights_Variation"},{"PuzzleId":"rzlrl","Fen":"rnbq3r/pp2bkpp/8/8/3P4/1QP2N2/P4PPP/R1B1K2R b KQ - 1 11","Moves":"c8e6 f3e5 f7e8 b3e6","Rating":1785,"NbPlays":217,"Popularity":83,"Themes":"crushing deflection opening short","OpeningFamily":"","Opening":"","OpeningVariation":"","ECO":"","OpeningTags":"Tarrasch_Defense Tarrasch_Defense_Two_Knights_Variation"},{"PuzzleId":"OFNGm","Fen":"r2q1rk1/pp2b1pp/2n1b3/2pp1p2/3PnBP1/2N2N1P/PP2PPB1/2RQ1RK1 w - - 0 12","Moves":"d4c5 f5g4 f3d4 c6d4","Rating":2049,"NbPlays":99,"Popularity":73,"Themes":"advantage master opening short","OpeningFamily":"","Opening":"","OpeningVariation":"","ECO":"","OpeningTags":"Tarrasch_Defense Tarrasch_Defense_Two_Knights_Variation"},{"PuzzleId":"XTmWa","Fen":"r1b2rk1/4nppp/p1n5/1p1q4/3p4/N3PN2/PP1Q1PPP/2R1KB1R b K - 0 15","Moves":"d4e3 d2d5 e7d5 c1c6","Rating":1165,"NbPlays":19225,"Popularity":96,"Themes":"advantage capturingDefender master opening short","OpeningFamily":"","Opening":"","OpeningVariation":"","ECO":"","OpeningTags":"Tarrasch_Defense Tarrasch_Defense_Two_Knights_Variation"},{"PuzzleId":"Dt5m2","Fen":"r1bqk1nr/pp3ppp/8/8/1n1pN3/5N2/PP2PPPP/R2QKB1R w KQkq - 0 12","Moves":"f3d4 d8d4 d1d4 b4c2 e1d2 c2d4","Rating":1402,"NbPlays":139,"Popularity":100,"Themes":"advantage attraction fork long opening sacrifice","OpeningFamily":"","Opening":"","OpeningVariation":"","ECO":"","OpeningTags":"Tarrasch_Defense Tarrasch_Defense_Two_Knights_Variation"},{"PuzzleId":"QpqWY","Fen":"r2q1rk1/p4ppp/1pb2n2/2b3B1/N2p4/4PN2/PP3PPP/R2Q1RK1 w - - 0 14","Moves":"f3d4 c5d4 d1d4 d8d4","Rating":1487,"NbPlays":149,"Popularity":17,"Themes":"advantage opening short","OpeningFamily":"","Opening":"","OpeningVariation":"","ECO":"","OpeningTags":"Tarrasch_Defense Tarrasch_Defense_Two_Knights_Variation"},{"PuzzleId":"HHDoB","Fen":"r1bqk2r/pp3ppp/5n2/2bp4/3P4/2N3P1/PP3PBP/R1BQK2R b KQkq - 0 10","Moves":"c5b4 d1a4 c8d7 a4b4","Rating":1430,"NbPlays":277,"Popularity":79,"Themes":"crushing fork opening short","OpeningFamily":"","Opening":"","OpeningVariation":"","ECO":"","OpeningTags":"Tarrasch_Defense Tarrasch_Defense_Two_Knights_Variation"},{"PuzzleId":"6ONc4","Fen":"r1bqk2r/pp2nppp/2n5/2P5/3p4/2N2N2/PP2PPPP/R2QKB1R w KQkq - 0 9","Moves":"c3b5 d8a5 d1d2 a5b5","Rating":1193,"NbPlays":65,"Popularity":83,"Themes":"advantage fork opening short","OpeningFamily":"","Opening":"","OpeningVariation":"","ECO":"","OpeningTags":"Tarrasch_Defense Tarrasch_Defense_Two_Knights_Variation"},{"PuzzleId":"rNHZh","Fen":"r2qkbnr/pp1b1ppp/2n5/3p4/Q1pP1B2/2N2N2/PP2PPPP/R3KB1R w KQkq - 4 8","Moves":"c3d5 c6b4 a4d1 b4d5","Rating":2320,"NbPlays":107,"Popularity":69,"Themes":"advantage opening short","OpeningFamily":"","Opening":"","OpeningVariation":"","ECO":"","OpeningTags":"Tarrasch_Defense Tarrasch_Defense_Two_Knights_Variation"},{"PuzzleId":"l5hG2","Fen":"r1b1kb1r/pp3p1p/1q3p2/8/1n6/1QN2N2/PP2PPPP/R3KB1R w KQkq - 3 11","Moves":"a2a3 b4d3 e2d3 b6b3","Rating":1475,"NbPlays":6526,"Popularity":93,"Themes":"advantage discoveredAttack opening short","OpeningFamily":"","Opening":"","OpeningVariation":"","ECO":"","OpeningTags":"Tarrasch_Defense Tarrasch_Defense_Two_Knights_Variation"},{"PuzzleId":"ZwDSP","Fen":"3rk1nr/pp3ppp/2nQb3/q7/8/2N2N2/PP2PPPP/R1B1KB1R w KQk - 3 11","Moves":"d6a3 c6b4 a3b4 a5b4","Rating":1882,"NbPlays":8020,"Popularity":93,"Themes":"advantage opening short","OpeningFamily":"","Opening":"","OpeningVariation":"","ECO":"","OpeningTags":"Tarrasch_Defense Tarrasch_Defense_Two_Knights_Variation"},{"PuzzleId":"bgmQZ","Fen":"rBbqk2r/pp3ppp/5n2/3p4/1b1N4/2N5/PP2PPPP/R2QKB1R b KQkq - 0 8","Moves":"a8b8 d1a4 b7b5 a4b4","Rating":1205,"NbPlays":378,"Popularity":100,"Themes":"advantage fork opening short","OpeningFamily":"","Opening":"","OpeningVariation":"","ECO":"","OpeningTags":"Tarrasch_Defense Tarrasch_Defense_Two_Knights_Variation"},{"PuzzleId":"RHpp6","Fen":"rnb1k2r/pp3ppp/5n2/q2p2B1/3N4/P1P5/4PPPP/R2QKB1R w KQkq - 1 10","Moves":"g5f6 a5c3 d1d2 c3a1","Rating":938,"NbPlays":821,"Popularity":88,"Themes":"crushing deflection opening short","OpeningFamily":"","Opening":"","OpeningVariation":"","ECO":"","OpeningTags":"Tarrasch_Defense Tarrasch_Defense_Two_Knights_Variation"},{"PuzzleId":"2LFTs","Fen":"r1b2knr/ppN2ppp/2N5/8/1b6/4B1P1/Pq2PP1P/R2QKB1R w KQ - 1 12","Moves":"e3d2 b4d2 d1d2 b2a1","Rating":1034,"NbPlays":1519,"Popularity":94,"Themes":"crushing opening short","OpeningFamily":"","Opening":"","OpeningVariation":"","ECO":"","OpeningTags":"Tarrasch_Defense Tarrasch_Defense_Two_Knights_Variation"},{"PuzzleId":"wgOkx","Fen":"rnb4r/ppN1kppp/8/2b5/8/5N2/Pq2PPPP/R2QKB1R w KQ - 2 11","Moves":"a1b1 c5b4 f3d2 b4d2 d1d2 b2b1","Rating":1265,"NbPlays":5409,"Popularity":94,"Themes":"advantage long opening","OpeningFamily":"","Opening":"","OpeningVariation":"","ECO":"","OpeningTags":"Tarrasch_Defense Tarrasch_Defense_Two_Knights_Variation"},{"PuzzleId":"hGwMp","Fen":"rn1q1rk1/pp3ppp/5b2/2Pp4/6b1/2N1PN2/PP3PPP/R2QKB1R w KQ - 0 10","Moves":"d1d5 f6c3 b2c3 d8d5","Rating":1229,"NbPlays":133,"Popularity":73,"Themes":"crushing intermezzo opening short","OpeningFamily":"","Opening":"","OpeningVariation":"","ECO":"","OpeningTags":"Tarrasch_Defense Tarrasch_Defense_Two_Knights_Variation"},{"PuzzleId":"ZyUMo","Fen":"2kr1qr1/pp3b1p/2nb1p2/3p4/1P6/P1N1P3/1B2BPPP/R2Q1RK1 w - - 3 18","Moves":"c3b5 d6h2 g1h2 f8h6 h2g1 h6h3","Rating":2493,"NbPlays":2680,"Popularity":90,"Themes":"advantage attraction kingsideAttack long master opening pin sacrifice","OpeningFamily":"","Opening":"","OpeningVariation":"","ECO":"","OpeningTags":"Tarrasch_Defense Tarrasch_Defense_Two_Knights_Variation"},{"PuzzleId":"8Vg4w","Fen":"r1b1k1nr/pp3ppp/2n5/1B6/8/q4N2/P2B1PPP/1R1QK2R b Kkq - 3 14","Moves":"g8e7 d2b4 a3a2 e1g1","Rating":2608,"NbPlays":357,"Popularity":85,"Themes":"advantage castling defensiveMove opening short","OpeningFamily":"","Opening":"","OpeningVariation":"","ECO":"","OpeningTags":"Tarrasch_Defense Tarrasch_Defense_Two_Knights_Variation"},{"PuzzleId":"lweSB","Fen":"r1b1k1nr/pp3ppp/2N5/3p4/8/1Pq5/P3P1PP/R1BQ1BKR w kq - 0 11","Moves":"c1b2 c3e3","Rating":1197,"NbPlays":1596,"Popularity":96,"Themes":"master mate mateIn1 oneMove opening","OpeningFamily":"","Opening":"","OpeningVariation":"","ECO":"","OpeningTags":"Tarrasch_Defense Tarrasch_Defense_Two_Knights_Variation"},{"PuzzleId":"ikmqN","Fen":"1brr2k1/p2q1ppp/4bn2/2pp4/3N4/BP2PB2/P4PPP/2RQ1RK1 w - - 0 18","Moves":"a3c5 c8c5 c1c5 d7d6 g2g3 d6c5","Rating":1928,"NbPlays":459,"Popularity":92,"Themes":"advantage attraction long opening sacrifice","OpeningFamily":"","Opening":"","OpeningVariation":"","ECO":"","OpeningTags":"Tarrasch_Defense Tarrasch_Defense_Two_Knights_Variation"},{"PuzzleId":"ZPouC","Fen":"r1b2rk1/1pb2ppp/p2q4/3pn3/P3n3/1PNBPN1P/1B3PP1/2RQ1RK1 w - - 3 19","Moves":"d3e4 e5f3 g2f3 d6h2","Rating":1689,"NbPlays":3514,"Popularity":93,"Themes":"clearance kingsideAttack mate mateIn2 opening short","OpeningFamily":"","Opening":"","OpeningVariation":"","ECO":"","OpeningTags":"Tarrasch_Defense Tarrasch_Defense_Two_Knights_Variation"},{"PuzzleId":"rF7iu","Fen":"r1b1k2r/pp2qppp/2n4n/3p4/Q1pPP3/2B5/PP1N1PPP/R3KB1R w KQkq - 3 11","Moves":"c3b4 e7b4 a4b4 c6b4","Rating":1087,"NbPlays":278,"Popularity":89,"Themes":"advantage opening short","OpeningFamily":"","Opening":"","OpeningVariation":"","ECO":"","OpeningTags":"Tarrasch_Defense Tarrasch_Defense_Two_Knights_Variation"},{"PuzzleId":"eNHdp","Fen":"rn1r2k1/pp3ppp/5n2/q7/N2p2b1/P5PP/1P1NPP2/2RQKB1R b K - 0 14","Moves":"g4f3 b2b4 a5a4 d1a4","Rating":2252,"NbPlays":311,"Popularity":86,"Themes":"advantage master opening short","OpeningFamily":"","Opening":"","OpeningVariation":"","ECO":"","OpeningTags":"Tarrasch_Defense Tarrasch_Defense_Two_Knights_Variation"},{"PuzzleId":"kDOjy","Fen":"rBbqk1nr/pp3pp1/7p/3p4/1bpPP3/2N2N2/PP3PPP/R2QKB1R b KQkq - 0 8","Moves":"a8b8 d1a4 b7b5 a4b4","Rating":1064,"NbPlays":1468,"Popularity":91,"Themes":"crushing fork opening short","OpeningFamily":"","Opening":"","OpeningVariation":"","ECO":"","OpeningTags":"Tarrasch_Defense Tarrasch_Defense_Two_Knights_Variation"},{"PuzzleId":"RUU7M","Fen":"r1b1k1nr/pp3ppp/2n5/3q4/QbpP4/2N2N2/PP3PPP/R1B1KB1R w KQkq - 2 9","Moves":"a4b4 d5e6 f1e2 c6b4","Rating":1746,"NbPlays":592,"Popularity":94,"Themes":"crushing intermezzo opening short","OpeningFamily":"","Opening":"","OpeningVariation":"","ECO":"","OpeningTags":"Tarrasch_Defense Tarrasch_Defense_Two_Knights_Variation"},{"PuzzleId":"Fq3TE","Fen":"r3kb1r/pp1b1pp1/2nq3p/3NN3/2pP4/8/PPQ1PPPP/R3KB1R w KQkq - 1 12","Moves":"e5c6 d6d5 e2e4 d5c6","Rating":1611,"NbPlays":7,"Popularity":0,"Themes":"advantage hangingPiece opening short","OpeningFamily":"","Opening":"","OpeningVariation":"","ECO":"","OpeningTags":"Tarrasch_Defense Tarrasch_Defense_Two_Knights_Variation"},{"PuzzleId":"lIiEg","Fen":"1br2rk1/1pq3pp/p3pn2/3p4/1P1N4/P3Pn2/1B2BPPP/2RQ1RK1 w - - 4 18","Moves":"e2f3 c7h2","Rating":977,"NbPlays":109,"Popularity":92,"Themes":"kingsideAttack mate mateIn1 oneMove opening","OpeningFamily":"","Opening":"","OpeningVariation":"","ECO":"","OpeningTags":"Tarrasch_Defense Tarrasch_Defense_Two_Knights_Variation"},{"PuzzleId":"J5LFX","Fen":"rnbq1rk1/pp3ppp/5b2/2Pp4/8/2N2N2/PP2PPPP/R2QKB1R w KQ - 0 9","Moves":"d1d5 f6c3 b2c3 d8d5","Rating":969,"NbPlays":2519,"Popularity":94,"Themes":"crushing intermezzo opening short","OpeningFamily":"","Opening":"","OpeningVariation":"","ECO":"","OpeningTags":"Tarrasch_Defense Tarrasch_Defense_Two_Knights_Variation"},{"PuzzleId":"evxms","Fen":"r2qkbnr/pQ1n1ppp/4b3/3p4/3P4/2N2N2/P3PPPP/R1B1KB1R w KQkq - 1 9","Moves":"c3d5 d8a5 c1d2 a5d5 b7d5 e6d5","Rating":1505,"NbPlays":3164,"Popularity":92,"Themes":"advantage long opening","OpeningFamily":"","Opening":"","OpeningVariation":"","ECO":"","OpeningTags":"Tarrasch_Defense Tarrasch_Defense_Two_Knights_Variation"},{"PuzzleId":"KZazV","Fen":"Nnbk1b1r/pp3p1p/5p2/8/2pP4/5N2/Pq2PPPP/R2QKB1R w KQ - 0 11","Moves":"a1c1 f8b4 f3d2 c4c3 c1c2 c3d2","Rating":1636,"NbPlays":42,"Popularity":93,"Themes":"advancedPawn crushing long master opening","OpeningFamily":"","Opening":"","OpeningVariation":"","ECO":"","OpeningTags":"Tarrasch_Defense Tarrasch_Defense_Two_Knights_Variation"},{"PuzzleId":"am8j0","Fen":"1br2rk1/1p3ppp/p1nq1n2/3p3b/1P1N4/P1N1P2P/1B2BPP1/2RQ1R1K w - - 5 17","Moves":"e2h5 d6h2","Rating":908,"NbPlays":192,"Popularity":63,"Themes":"mate mateIn1 oneMove opening","OpeningFamily":"","Opening":"","OpeningVariation":"","ECO":"","OpeningTags":"Tarrasch_Defense Tarrasch_Defense_Two_Knights_Variation"},{"PuzzleId":"t4O9s","Fen":"r1b1kb1r/1p3ppp/pNnq4/8/3P4/PQ6/1P3PPP/R3KB1R b KQkq - 4 14","Moves":"d6e6 b3e6 f7e6 b6a8","Rating":1683,"NbPlays":2452,"Popularity":92,"Themes":"advantage opening short","OpeningFamily":"","Opening":"","OpeningVariation":"","ECO":"","OpeningTags":"Tarrasch_Defense Tarrasch_Defense_Two_Knights_Variation"},{"PuzzleId":"RcVnF","Fen":"r2qkbnr/pp3ppp/2n5/2P5/3p1Bb1/2N2N2/PP2PPPP/R2QKB1R w KQkq - 0 8","Moves":"c3b5 d8a5 f4d2 a5b5","Rating":1364,"NbPlays":210,"Popularity":65,"Themes":"advantage fork opening short","OpeningFamily":"","Opening":"","OpeningVariation":"","ECO":"","OpeningTags":"Tarrasch_Defense Tarrasch_Defense_Two_Knights_Variation"},{"PuzzleId":"WO8n1","Fen":"r1b2k1r/pp3ppp/2nN1b2/q1P5/3p4/1Q6/PP1NPPPP/R3KB1R b KQ - 5 14","Moves":"a5c5 b3f7","Rating":674,"NbPlays":1116,"Popularity":95,"Themes":"mate mateIn1 oneMove opening","OpeningFamily":"","Opening":"","OpeningVariation":"","ECO":"","OpeningTags":"Tarrasch_Defense Tarrasch_Defense_Two_Knights_Variation"},{"PuzzleId":"bAZ7l","Fen":"3qkbnr/Q2b1ppp/8/3NP3/2p5/4P3/Pr2P1PP/3RKB1R b Kk - 0 14","Moves":"g8h6 d5c7 d8c7 a7c7 f8b4 e1f2","Rating":1277,"NbPlays":115,"Popularity":100,"Themes":"advantage long opening","OpeningFamily":"","Opening":"","OpeningVariation":"","ECO":"","OpeningTags":"Tarrasch_Defense Tarrasch_Defense_Two_Knights_Variation"},{"PuzzleId":"00Htd","Fen":"rnbqk2r/1p3ppp/p4b2/2Pp4/8/2N2N2/PP2PPPP/R2QKB1R w KQkq - 0 9","Moves":"d1d5 f6c3 b2c3 d8d5","Rating":950,"NbPlays":1113,"Popularity":94,"Themes":"crushing intermezzo opening short","OpeningFamily":"","Opening":"","OpeningVariation":"","ECO":"","OpeningTags":"Tarrasch_Defense Tarrasch_Defense_Two_Knights_Variation"},{"PuzzleId":"utEmJ","Fen":"r1b2rk1/pp1n1ppp/8/q5B1/1b2n3/2N1PN2/PPQ2PPP/R3KB1R w KQ - 5 12","Moves":"c2e4 b4c3 b2c3 a5c3 f3d2 c3a1","Rating":861,"NbPlays":1107,"Popularity":94,"Themes":"advantage fork long opening","OpeningFamily":"","Opening":"","OpeningVariation":"","ECO":"","OpeningTags":"Tarrasch_Defense Tarrasch_Defense_Two_Knights_Variation"},{"PuzzleId":"rkLTc","Fen":"r1bqk2r/pp3ppp/2n2b2/3p4/8/1QN2N2/PP2PPPP/R3KB1R w KQkq - 0 10","Moves":"b3d5 f6c3 b2c3 d8d5","Rating":1010,"NbPlays":307,"Popularity":90,"Themes":"crushing intermezzo opening short","OpeningFamily":"","Opening":"","OpeningVariation":"","ECO":"","OpeningTags":"Tarrasch_Defense Tarrasch_Defense_Two_Knights_Variation"},{"PuzzleId":"QPeQN","Fen":"rnbqk2r/1p3ppp/p4n2/2bN4/4P3/5N2/PP1B1PPP/R2QKB1R b KQkq - 0 12","Moves":"f6e4 d1a4 b8c6 a4e4","Rating":1344,"NbPlays":2961,"Popularity":92,"Themes":"crushing fork opening short","OpeningFamily":"","Opening":"","OpeningVariation":"","ECO":"","OpeningTags":"Tarrasch_Defense Tarrasch_Defense_Two_Knights_Variation"},{"PuzzleId":"kXXRF","Fen":"r1b1k2r/1p3pp1/pNn5/8/3N2n1/P3P1q1/1P4B1/R1BQ1RK1 w kq - 0 18","Moves":"f1f3 h8h1 g1h1 g3h2","Rating":1915,"NbPlays":201,"Popularity":78,"Themes":"attraction kingsideAttack mate mateIn2 opening pin sacrifice short","OpeningFamily":"","Opening":"","OpeningVariation":"","ECO":"","OpeningTags":"Tarrasch_Defense Tarrasch_Defense_Two_Knights_Variation"},{"PuzzleId":"O33LF","Fen":"rn1q1rk1/pp1b1ppp/5b2/1B6/3Np3/2N5/PP3PPP/R2Q1RK1 w - - 4 12","Moves":"c3e4 f6d4 d1d4 d7b5 d4d8 f8d8","Rating":1701,"NbPlays":673,"Popularity":89,"Themes":"advantage capturingDefender long opening","OpeningFamily":"","Opening":"","OpeningVariation":"","ECO":"","OpeningTags":"Tarrasch_Defense Tarrasch_Defense_Two_Knights_Variation"},{"PuzzleId":"bly6g","Fen":"rnb1k2r/pp3ppp/3b4/4q3/2B1p3/8/PP1N1PPP/R1BQ1RK1 w kq - 2 12","Moves":"d2e4 e5h2","Rating":742,"NbPlays":137,"Popularity":74,"Themes":"kingsideAttack mate mateIn1 oneMove opening","OpeningFamily":"","Opening":"","OpeningVariation":"","ECO":"","OpeningTags":"Tarrasch_Defense Tarrasch_Defense_Two_Knights_Variation"},{"PuzzleId":"mvTxR","Fen":"r3kbnr/p4ppp/2p1b3/q7/8/5N2/PB3PPP/R2QR1K1 b kq - 2 13","Moves":"h7h6 e1e6 f7e6 f3e5 g8f6 d1c2","Rating":2654,"NbPlays":255,"Popularity":81,"Themes":"advantage long opening sacrifice","OpeningFamily":"","Opening":"","OpeningVariation":"","ECO":"","OpeningTags":"Tarrasch_Defense Tarrasch_Defense_Two_Knights_Variation"},{"PuzzleId":"0c6Xz","Fen":"r1b1k2r/pp2qppp/2n2n2/1B6/8/4pN2/PP1B1PPP/2RQK2R w Kkq - 0 13","Moves":"d2e3 e7b4 d1d2 b4b5","Rating":1125,"NbPlays":258,"Popularity":82,"Themes":"crushing fork master opening short","OpeningFamily":"","Opening":"","OpeningVariation":"","ECO":"","OpeningTags":"Tarrasch_Defense Tarrasch_Defense_Two_Knights_Variation"},{"PuzzleId":"BJyI3","Fen":"1br2rk1/p1qb1pp1/2p4p/2Np2n1/8/1P2PN1P/PB3PP1/2RQ1RK1 w - - 9 19","Moves":"c5d7 g5f3 g2f3 c7h2","Rating":1426,"NbPlays":8463,"Popularity":93,"Themes":"kingsideAttack mate mateIn2 opening short","OpeningFamily":"","Opening":"","OpeningVariation":"","ECO":"","OpeningTags":"Tarrasch_Defense Tarrasch_Defense_Two_Knights_Variation"},{"PuzzleId":"J3Tt6","Fen":"rnb2rk1/pp3ppp/8/3N2q1/3Nn3/1Q2P3/PP3PPP/R3KB1R w KQ - 1 12","Moves":"d5c7 g5a5 b3c3 e4c3","Rating":1487,"NbPlays":859,"Popularity":94,"Themes":"crushing fork opening short","OpeningFamily":"","Opening":"","OpeningVariation":"","ECO":"","OpeningTags":"Tarrasch_Defense Tarrasch_Defense_Two_Knights_Variation"},{"PuzzleId":"C6hOY","Fen":"r2qkbnr/pp3ppp/2n5/2P5/N2p4/4Pb2/PP3PPP/R1BQKB1R w KQkq - 0 9","Moves":"d1f3 d8a5 c1d2 a5a4","Rating":1157,"NbPlays":51,"Popularity":63,"Themes":"advantage fork master opening short","OpeningFamily":"","Opening":"","OpeningVariation":"","ECO":"","OpeningTags":"Tarrasch_Defense Tarrasch_Defense_Two_Knights_Variation"},{"PuzzleId":"45HnC","Fen":"r2qr1k1/pp1b1ppp/2nb1n2/1B1p4/1P1N4/P1N1P3/1B3PPP/R2Q1RK1 b - - 2 12","Moves":"d6h2 g1h2 f6g4 h2g1","Rating":1334,"NbPlays":6062,"Popularity":90,"Themes":"advantage defensiveMove hangingPiece opening short","OpeningFamily":"","Opening":"","OpeningVariation":"","ECO":"","OpeningTags":"Tarrasch_Defense Tarrasch_Defense_Two_Knights_Variation"},{"PuzzleId":"AYWiR","Fen":"r1b1k1nr/pp2qppp/8/8/1n1p4/5N2/P2BPPPP/2RQKB1R w Kkq - 2 12","Moves":"f3d4 b4d3","Rating":1057,"NbPlays":4081,"Popularity":97,"Themes":"master mate mateIn1 oneMove opening pin smotheredMate","OpeningFamily":"","Opening":"","OpeningVariation":"","ECO":"","OpeningTags":"Tarrasch_Defense Tarrasch_Defense_Two_Knights_Variation"},{"PuzzleId":"5s41q","Fen":"1br2rk1/1p3ppp/p1Bq1n2/3p4/1P6/P3Pb2/1B2NPPP/2RQ1RK1 w - - 0 17","Moves":"g2f3 d6h2","Rating":888,"NbPlays":58,"Popularity":100,"Themes":"kingsideAttack mate mateIn1 oneMove opening","OpeningFamily":"","Opening":"","OpeningVariation":"","ECO":"","OpeningTags":"Tarrasch_Defense Tarrasch_Defense_Two_Knights_Variation"},{"PuzzleId":"27EOe","Fen":"r2qk1nr/pp3ppp/4b3/8/1b6/4B3/PP1N1PPP/R2QKB1R b KQkq - 3 11","Moves":"g8f6 d1a4 e6d7 a4b4","Rating":1088,"NbPlays":679,"Popularity":88,"Themes":"crushing fork opening short","OpeningFamily":"","Opening":"","OpeningVariation":"","ECO":"","OpeningTags":"Tarrasch_Defense Tarrasch_Defense_Two_Knights_Variation"},{"PuzzleId":"LQCcO","Fen":"rn1q1rk1/pp1b1ppp/5b2/1B6/3Np3/2N5/PP3PPP/R2Q1RK1 w - - 0 12","Moves":"c3e4 f6d4 d1d4 d7b5","Rating":1700,"NbPlays":5828,"Popularity":95,"Themes":"advantage capturingDefender opening short","OpeningFamily":"","Opening":"","OpeningVariation":"","ECO":"","OpeningTags":"Tarrasch_Defense Tarrasch_Defense_Two_Knights_Variation"},{"PuzzleId":"OgP2K","Fen":"r3kbnr/pQ3ppp/4b3/2q5/8/4P3/PP3PPP/R1B1KB1R b KQkq - 0 13","Moves":"e6d5 f1b5 c5b5 b7b5","Rating":1081,"NbPlays":490,"Popularity":88,"Themes":"crushing opening short","OpeningFamily":"","Opening":"","OpeningVariation":"","ECO":"","OpeningTags":"Tarrasch_Defense Tarrasch_Defense_Two_Knights_Variation"},{"PuzzleId":"PWELv","Fen":"rn2k2r/ppN2ppp/4b3/2b5/8/5N2/Pq2PPPP/R2QKB1R b KQkq - 1 10","Moves":"e8f8 d1d8","Rating":875,"NbPlays":33,"Popularity":86,"Themes":"mate mateIn1 oneMove opening","OpeningFamily":"","Opening":"","OpeningVariation":"","ECO":"","OpeningTags":"Tarrasch_Defense Tarrasch_Defense_Two_Knights_Variation"},{"PuzzleId":"9S2Eu","Fen":"r1b2k1r/ppN2ppp/2n5/2b5/8/4PN2/Pq3PPP/R2QKB1R w KQ - 2 12","Moves":"a1b1 c5b4 f3d2 b4d2","Rating":1208,"NbPlays":7984,"Popularity":93,"Themes":"advantage opening short","OpeningFamily":"","Opening":"","OpeningVariation":"","ECO":"","OpeningTags":"Tarrasch_Defense Tarrasch_Defense_Two_Knights_Variation"},{"PuzzleId":"9Yuqy","Fen":"r2qk2r/ppbb1pp1/5n2/1P1p2Np/P1pP3n/2N1PB1P/3B1PP1/R2Q1RK1 w kq - 5 17","Moves":"f3d5 f6d5 c3d5 d8g5","Rating":1573,"NbPlays":128,"Popularity":85,"Themes":"advantage discoveredAttack opening short","OpeningFamily":"","Opening":"","OpeningVariation":"","ECO":"","OpeningTags":"Tarrasch_Defense Tarrasch_Defense_Two_Knights_Variation"},{"PuzzleId":"7Dc9y","Fen":"rnbq1rk1/pp3ppp/5b2/2Pp4/8/2N2N2/PP2PPPP/R2QKB1R w KQ - 1 9","Moves":"d1d5 f6c3 b2c3 d8d5","Rating":973,"NbPlays":1759,"Popularity":94,"Themes":"crushing intermezzo opening short","OpeningFamily":"","Opening":"","OpeningVariation":"","ECO":"","OpeningTags":"Tarrasch_Defense Tarrasch_Defense_Two_Knights_Variation"}]